{
  "items": [
    {
      "track": {
        "album": {
          "album_type": "album",
          "artists": [
            {
              "external_urls": {
                "spotify": "https://open.spotify.com/artist/5rTe87Iq7oBm6cKlPCjsz0"
              },
              "href": "https://api.spotify.com/v1/artists/5rTe87Iq7oBm6cKlPCjsz0",
              "id": "5rTe87Iq7oBm6cKlPCjsz0",
              "name": "All Shall Be Well (and All Shall Be Well and All Manner of Things Shall Be Well)",
              "type": "artist",
              "uri": "spotify:artist:5rTe87Iq7oBm6cKlPCjsz0"
            }
          ],
          "available_markets": [
            "AD",
            "AE",
            "AG",
            "AL",
            "AM",
            "AO",
            "AR",
            "AT",
            "AU",
            "AZ",
            "BA",
            "BB",
            "BD",
            "BE",
            "BF",
            "BG",
            "BH",
            "BI",
            "BJ",
            "BN",
            "BO",
            "BR",
            "BS",
            "BT",
            "BW",
            "BY",
            "BZ",
            "CA",
            "CD",
            "CG",
            "CH",
            "CI",
            "CL",
            "CM",
            "CO",
            "CR",
            "CV",
            "CW",
            "CY",
            "CZ",
            "DE",
            "DJ",
            "DK",
            "DM",
            "DO",
            "DZ",
            "EC",
            "EE",
            "EG",
            "ES",
            "FI",
            "FJ",
            "FM",
            "FR",
            "GA",
            "GB",
            "GD",
            "GE",
            "GH",
            "GM",
            "GN",
            "GQ",
            "GR",
            "GT",
            "GW",
            "GY",
            "HK",
            "HN",
            "HR",
            "HT",
            "HU",
            "ID",
            "IE",
            "IL",
            "IN",
            "IQ",
            "IS",
            "IT",
            "JM",
            "JO",
            "JP",
            "KE",
            "KG",
            "KH",
            "KI",
            "KM",
            "KN",
            "KR",
            "KW",
            "KZ",
            "LA",
            "LB",
            "LC",
            "LI",
            "LK",
            "LR",
            "LS",
            "LT",
            "LU",
            "LV",
            "LY",
            "MA",
            "MC",
            "MD",
            "ME",
            "MG",
            "MH",
            "MK",
            "ML",
            "MN",
            "MO",
            "MR",
            "MT",
            "MU",
            "MV",
            "MW",
            "MX",
            "MY",
            "MZ",
            "NA",
            "NE",
            "NG",
            "NI",
            "NL",
            "NO",
            "NP",
            "NR",
            "NZ",
            "OM",
            "PA",
            "PE",
            "PG",
            "PH",
            "PK",
            "PL",
            "PS",
            "PT",
            "PW",
            "PY",
            "QA",
            "RO",
            "RS",
            "RW",
            "SA",
            "SB",
            "SC",
            "SE",
            "SG",
            "SI",
            "SK",
            "SL",
            "SM",
            "SN",
            "SR",
            "ST",
            "SV",
            "SZ",
            "TD",
            "TG",
            "TH",
            "TJ",
            "TL",
            "TN",
            "TO",
            "TR",
            "TT",
            "TV",
            "TW",
            "TZ",
            "UA",
            "UG",
            "US",
            "UY",
            "UZ",
            "VC",
            "VE",
            "VN",
            "VU",
            "WS",
            "XK",
            "ZA",
            "ZM",
            "ZW"
          ],
          "external_urls": {
            "spotify": "https://open.spotify.com/album/4GZscfgaPVCCXP3ggbEGjs"
          },
          "href": "https://api.spotify.com/v1/albums/4GZscfgaPVCCXP3ggbEGjs",
          "id": "4GZscfgaPVCCXP3ggbEGjs",
          "images": [
            {
              "height": 640,
              "url": "https://i.scdn.co/image/ab67616d0000b27305eec0e4228a3e994cb1fe7b",
              "width": 640
            },
            {
              "height": 300,
              "url": "https://i.scdn.co/image/ab67616d00001e0205eec0e4228a3e994cb1fe7b",
              "width": 300
            },
            {
              "height": 64,
              "url": "https://i.scdn.co/image/ab67616d0000485105eec0e4228a3e994cb1fe7b",
              "width": 64
            }
          ],
          "name": "Zwartgroen",
          "release_date": "2020-02-20",
          "release_date_precision": "day",
          "total_tracks": 7,
          "type": "album",
          "uri": "spotify:album:4GZscfgaPVCCXP3ggbEGjs"
        },
        "artists": [
          {
            "external_urls": {
              "spotify": "https://open.spotify.com/artist/5rTe87Iq7oBm6cKlPCjsz0"
            },
            "href": "https://api.spotify.com/v1/artists/5rTe87Iq7oBm6cKlPCjsz0",
            "id": "5rTe87Iq7oBm6cKlPCjsz0",
            "name": "All Shall Be Well (and All Shall Be Well and All Manner of Things Shall Be Well)",
            "type": "artist",
            "uri": "spotify:artist:5rTe87Iq7oBm6cKlPCjsz0"
          }
        ],
        "available_markets": [
          "AD",
          "AE",
          "AG",
          "AL",
          "AM",
          "AO",
          "AR",
          "AT",
          "AU",
          "AZ",
          "BA",
          "BB",
          "BD",
          "BE",
          "BF",
          "BG",
          "BH",
          "BI",
          "BJ",
          "BN",
          "BO",
          "BR",
          "BS",
          "BT",
          "BW",
          "BY",
          "BZ",
          "CA",
          "CD",
          "CG",
          "CH",
          "CI",
          "CL",
          "CM",
          "CO",
          "CR",
          "CV",
          "CW",
          "CY",
          "CZ",
          "DE",
          "DJ",
          "DK",
          "DM",
          "DO",
          "DZ",
          "EC",
          "EE",
          "EG",
          "ES",
          "FI",
          "FJ",
          "FM",
          "FR",
          "GA",
          "GB",
          "GD",
          "GE",
          "GH",
          "GM",
          "GN",
          "GQ",
          "GR",
          "GT",
          "GW",
          "GY",
          "HK",
          "HN",
          "HR",
          "HT",
          "HU",
          "ID",
          "IE",
          "IL",
          "IN",
          "IQ",
          "IS",
          "IT",
          "JM",
          "JO",
          "JP",
          "KE",
          "KG",
          "KH",
          "KI",
          "KM",
          "KN",
          "KR",
          "KW",
          "KZ",
          "LA",
          "LB",
          "LC",
          "LI",
          "LK",
          "LR",
          "LS",
          "LT",
          "LU",
          "LV",
          "LY",
          "MA",
          "MC",
          "MD",
          "ME",
          "MG",
          "MH",
          "MK",
          "ML",
          "MN",
          "MO",
          "MR",
          "MT",
          "MU",
          "MV",
          "MW",
          "MX",
          "MY",
          "MZ",
          "NA",
          "NE",
          "NG",
          "NI",
          "NL",
          "NO",
          "NP",
          "NR",
          "NZ",
          "OM",
          "PA",
          "PE",
          "PG",
          "PH",
          "PK",
          "PL",
          "PS",
          "PT",
          "PW",
          "PY",
          "QA",
          "RO",
          "RS",
          "RW",
          "SA",
          "SB",
          "SC",
          "SE",
          "SG",
          "SI",
          "SK",
          "SL",
          "SM",
          "SN",
          "SR",
          "ST",
          "SV",
          "SZ",
          "TD",
          "TG",
          "TH",
          "TJ",
          "TL",
          "TN",
          "TO",
          "TR",
          "TT",
          "TV",
          "TW",
          "TZ",
          "UA",
          "UG",
          "US",
          "UY",
          "UZ",
          "VC",
          "VE",
          "VN",
          "VU",
          "WS",
          "XK",
          "ZA",
          "ZM",
          "ZW"
        ],
        "disc_number": 1,
        "duration_ms": 441448,
        "explicit": false,
        "external_ids": {
          "isrc": "NLQT82000004"
        },
        "external_urls": {
          "spotify": "https://open.spotify.com/track/7gQ3VAMWqQQrSZQhN0c6cL"
        },
        "href": "https://api.spotify.com/v1/tracks/7gQ3VAMWqQQrSZQhN0c6cL",
        "id": "7gQ3VAMWqQQrSZQhN0c6cL",
        "is_local": false,
        "name": "Beyond Us, Only Darkness",
        "popularity": 13,
        "preview_url": "https://p.scdn.co/mp3-preview/c691b044234f81b9b6daadf0bc6ad70e60625f94?cid=d91479fbfab04b6b84bc68559d2f97d2",
        "track_number": 4,
        "type": "track",
        "uri": "spotify:track:7gQ3VAMWqQQrSZQhN0c6cL"
      },
      "played_at": "2022-12-02T03:47:10.941Z",
      "context": {
        "external_urls": {
          "spotify": "https://open.spotify.com/playlist/5rPBW39Qw8IxJdLnKUgUNk"
        },
        "href": "https://api.spotify.com/v1/playlists/5rPBW39Qw8IxJdLnKUgUNk",
        "type": "playlist",
        "uri": "spotify:playlist:5rPBW39Qw8IxJdLnKUgUNk"
      }
    },
    {
      "track": {
        "album": {
          "album_type": "single",
          "artists": [
            {
              "external_urls": {
                "spotify": "https://open.spotify.com/artist/2UmVsCJpQoAGPcaKbCyheW"
              },
              "href": "https://api.spotify.com/v1/artists/2UmVsCJpQoAGPcaKbCyheW",
              "id": "2UmVsCJpQoAGPcaKbCyheW",
              "name": "เรนิษรา",
              "type": "artist",
              "uri": "spotify:artist:2UmVsCJpQoAGPcaKbCyheW"
            }
          ],
          "available_markets": [
            "AD",
            "AE",
            "AG",
            "AL",
            "AM",
            "AO",
            "AR",
            "AT",
            "AU",
            "AZ",
            "BA",
            "BB",
            "BD",
            "BE",
            "BF",
            "BG",
            "BH",
            "BI",
            "BJ",
            "BN",
            "BO",
            "BR",
            "BS",
            "BT",
            "BW",
            "BY",
            "BZ",
            "CA",
            "CD",
            "CG",
            "CH",
            "CI",
            "CL",
            "CM",
            "CO",
            "CR",
            "CV",
            "CW",
            "CY",
            "CZ",
            "DE",
            "DJ",
            "DK",
            "DM",
            "DO",
            "DZ",
            "EC",
            "EE",
            "EG",
            "ES",
            "FI",
            "FJ",
            "FM",
            "FR",
            "GA",
            "GB",
            "GD",
            "GE",
            "GH",
            "GM",
            "GN",
            "GQ",
            "GR",
            "GT",
            "GW",
            "GY",
            "HK",
            "HN",
            "HR",
            "HT",
            "HU",
            "ID",
            "IE",
            "IL",
            "IN",
            "IQ",
            "IS",
            "IT",
            "JM",
            "JO",
            "JP",
            "KE",
            "KG",
            "KH",
            "KI",
            "KM",
            "KN",
            "KR",
            "KW",
            "KZ",
            "LA",
            "LB",
            "LC",
            "LI",
            "LK",
            "LR",
            "LS",
            "LT",
            "LU",
            "LV",
            "LY",
            "MA",
            "MC",
            "MD",
            "ME",
            "MG",
            "MH",
            "MK",
            "ML",
            "MN",
            "MO",
            "MR",
            "MT",
            "MU",
            "MV",
            "MW",
            "MX",
            "MY",
            "MZ",
            "NA",
            "NE",
            "NG",
            "NI",
            "NL",
            "NO",
            "NP",
            "NR",
            "NZ",
            "OM",
            "PA",
            "PE",
            "PG",
            "PH",
            "PK",
            "PL",
            "PS",
            "PT",
            "PW",
            "PY",
            "QA",
            "RO",
            "RS",
            "RW",
            "SA",
            "SB",
            "SC",
            "SE",
            "SG",
            "SI",
            "SK",
            "SL",
            "SM",
            "SN",
            "SR",
            "ST",
            "SV",
            "SZ",
            "TD",
            "TG",
            "TH",
            "TJ",
            "TL",
            "TN",
            "TO",
            "TR",
            "TT",
            "TV",
            "TW",
            "TZ",
            "UA",
            "UG",
            "US",
            "UY",
            "UZ",
            "VC",
            "VE",
            "VN",
            "VU",
            "WS",
            "XK",
            "ZA",
            "ZM",
            "ZW"
          ],
          "external_urls": {
            "spotify": "https://open.spotify.com/album/3h5McsoCWje5uRcj8psVEH"
          },
          "href": "https://api.spotify.com/v1/albums/3h5McsoCWje5uRcj8psVEH",
          "id": "3h5McsoCWje5uRcj8psVEH",
          "images": [
            {
              "height": 640,
              "url": "https://i.scdn.co/image/ab67616d0000b27343faaca4a9abefb093fad34b",
              "width": 640
            },
            {
              "height": 300,
              "url": "https://i.scdn.co/image/ab67616d00001e0243faaca4a9abefb093fad34b",
              "width": 300
            },
            {
              "height": 64,
              "url": "https://i.scdn.co/image/ab67616d0000485143faaca4a9abefb093fad34b",
              "width": 64
            }
          ],
          "name": "ผู้ถูกเลือกให้ผิดหวัง (ดอกไม้ฤดูหนาว) [Sad flower]",
          "release_date": "2022-11-04",
          "release_date_precision": "day",
          "total_tracks": 1,
          "type": "album",
          "uri": "spotify:album:3h5McsoCWje5uRcj8psVEH"
        },
        "artists": [
          {
            "external_urls": {
              "spotify": "https://open.spotify.com/artist/2UmVsCJpQoAGPcaKbCyheW"
            },
            "href": "https://api.spotify.com/v1/artists/2UmVsCJpQoAGPcaKbCyheW",
            "id": "2UmVsCJpQoAGPcaKbCyheW",
            "name": "เรนิษรา",
            "type": "artist",
            "uri": "spotify:artist:2UmVsCJpQoAGPcaKbCyheW"
          }
        ],
        "available_markets": [
          "AD",
          "AE",
          "AG",
          "AL",
          "AM",
          "AO",
          "AR",
          "AT",
          "AU",
          "AZ",
          "BA",
          "BB",
          "BD",
          "BE",
          "BF",
          "BG",
          "BH",
          "BI",
          "BJ",
          "BN",
          "BO",
          "BR",
          "BS",
          "BT",
          "BW",
          "BY",
          "BZ",
          "CA",
          "CD",
          "CG",
          "CH",
          "CI",
          "CL",
          "CM",
          "CO",
          "CR",
          "CV",
          "CW",
          "CY",
          "CZ",
          "DE",
          "DJ",
          "DK",
          "DM",
          "DO",
          "DZ",
          "EC",
          "EE",
          "EG",
          "ES",
          "FI",
          "FJ",
          "FM",
          "FR",
          "GA",
          "GB",
          "GD",
          "GE",
          "GH",
          "GM",
          "GN",
          "GQ",
          "GR",
          "GT",
          "GW",
          "GY",
          "HK",
          "HN",
          "HR",
          "HT",
          "HU",
          "ID",
          "IE",
          "IL",
          "IN",
          "IQ",
          "IS",
          "IT",
          "JM",
          "JO",
          "JP",
          "KE",
          "KG",
          "KH",
          "KI",
          "KM",
          "KN",
          "KR",
          "KW",
          "KZ",
          "LA",
          "LB",
          "LC",
          "LI",
          "LK",
          "LR",
          "LS",
          "LT",
          "LU",
          "LV",
          "LY",
          "MA",
          "MC",
          "MD",
          "ME",
          "MG",
          "MH",
          "MK",
          "ML",
          "MN",
          "MO",
          "MR",
          "MT",
          "MU",
          "MV",
          "MW",
          "MX",
          "MY",
          "MZ",
          "NA",
          "NE",
          "NG",
          "NI",
          "NL",
          "NO",
          "NP",
          "NR",
          "NZ",
          "OM",
          "PA",
          "PE",
          "PG",
          "PH",
          "PK",
          "PL",
          "PS",
          "PT",
          "PW",
          "PY",
          "QA",
          "RO",
          "RS",
          "RW",
          "SA",
          "SB",
          "SC",
          "SE",
          "SG",
          "SI",
          "SK",
          "SL",
          "SM",
          "SN",
          "SR",
          "ST",
          "SV",
          "SZ",
          "TD",
          "TG",
          "TH",
          "TJ",
          "TL",
          "TN",
          "TO",
          "TR",
          "TT",
          "TV",
          "TW",
          "TZ",
          "UA",
          "UG",
          "US",
          "UY",
          "UZ",
          "VC",
          "VE",
          "VN",
          "VU",
          "WS",
          "XK",
          "ZA",
          "ZM",
          "ZW"
        ],
        "disc_number": 1,
        "duration_ms": 270033,
        "explicit": false,
        "external_ids": {
          "isrc": "DGA052254154"
        },
        "external_urls": {
          "spotify": "https://open.spotify.com/track/7BUHKcrvmr9WIAgEBkwukl"
        },
        "href": "https://api.spotify.com/v1/tracks/7BUHKcrvmr9WIAgEBkwukl",
        "id": "7BUHKcrvmr9WIAgEBkwukl",
        "is_local": false,
        "name": "ผู้ถูกเลือกให้ผิดหวัง (ดอกไม้ฤดูหนาว) - Sad flower",
        "popularity": 49,
        "preview_url": "https://p.scdn.co/mp3-preview/15f197a76402d78ed8a64fd74985fb177644279c?cid=d91479fbfab04b6b84bc68559d2f97d2",
        "track_number": 1,
        "type": "track",
        "uri": "spotify:track:7BUHKcrvmr9WIAgEBkwukl"
      },
      "played_at": "2022-12-02T03:54:14.560Z",
      "context": {
        "external_urls": {
          "spotify": "https://open.spotify.com/playlist/6PWn5SZO1bJtmg6OJvdCe4"
        },
        "href": "https://api.spotify.com/v1/playlists/6PWn5SZO1bJtmg6OJvdCe4",
        "type": "playlist",
        "uri": "spotify:playlist:6PWn5SZO1bJtmg6OJvdCe4"
      }
    },
    {
      "track": {
        "album": {
          "album_type": "single",
          "artists": [
            {
              "external_urls": {
                "spotify": "https://open.spotify.com/artist/7lhxw2OpjLMGTrlUobUN3F"
              },
              "href": "https://api.spotify.com/v1/artists/7lhxw2OpjLMGTrlUobUN3F",
              "id": "7lhxw2OpjLMGTrlUobUN3F",
              "name": "Uncle Ben",
              "type": "artist",
              "uri": "spotify:artist:7lhxw2OpjLMGTrlUobUN3F"
            }
          ],
          "available_markets": [
            "AD",
            "AE",
            "AG",
            "AL",
            "AM",
            "AO",
            "AR",
            "AT",
            "AU",
            "AZ",
            "BA",
            "BB",
            "BD",
            "BE",
            "BF",
            "BG",
            "BH",
            "BI",
            "BJ",
            "BN",
            "BO",
            "BR",
            "BS",
            "BT",
            "BW",
            "BY",
            "BZ",
            "CA",
            "CD",
            "CG",
            "CH",
            "CI",
            "CL",
            "CM",
            "CO",
            "CR",
            "CV",
            "CW",
            "CY",
            "CZ",
            "DE",
            "DJ",
            "DK",
            "DM",
            "DO",
            "DZ",
            "EC",
            "EE",
            "EG",
            "ES",
            "FI",
            "FJ",
            "FM",
            "FR",
            "GA",
            "GB",
            "GD",
            "GE",
            "GH",
            "GM",
            "GN",
            "GQ",
            "GR",
            "GT",
            "GW",
            "GY",
            "HK",
            "HN",
            "HR",
            "HT",
            "HU",
            "ID",
            "IE",
            "IL",
            "IN",
            "IQ",
            "IS",
            "IT",
            "JM",
            "JO",
            "JP",
            "KE",
            "KG",
            "KH",
            "KI",
            "KM",
            "KN",
            "KR",
            "KW",
            "KZ",
            "LA",
            "LB",
            "LC",
            "LI",
            "LK",
            "LR",
            "LS",
            "LT",
            "LU",
            "LV",
            "LY",
            "MA",
            "MC",
            "MD",
            "ME",
            "MG",
            "MH",
            "MK",
            "ML",
            "MN",
            "MO",
            "MR",
            "MT",
            "MU",
            "MV",
            "MW",
            "MX",
            "MY",
            "MZ",
            "NA",
            "NE",
            "NG",
            "NI",
            "NL",
            "NO",
            "NP",
            "NR",
            "NZ",
            "OM",
            "PA",
            "PE",
            "PG",
            "PH",
            "PK",
            "PL",
            "PS",
            "PT",
            "PW",
            "PY",
            "QA",
            "RO",
            "RS",
            "RW",
            "SA",
            "SB",
            "SC",
            "SE",
            "SG",
            "SI",
            "SK",
            "SL",
            "SM",
            "SN",
            "SR",
            "ST",
            "SV",
            "SZ",
            "TD",
            "TG",
            "TH",
            "TJ",
            "TL",
            "TN",
            "TO",
            "TR",
            "TT",
            "TV",
            "TW",
            "TZ",
            "UA",
            "UG",
            "US",
            "UY",
            "UZ",
            "VC",
            "VE",
            "VN",
            "VU",
            "WS",
            "XK",
            "ZA",
            "ZM",
            "ZW"
          ],
          "external_urls": {
            "spotify": "https://open.spotify.com/album/4RXn64FAasCSt8Tsyx8iMU"
          },
          "href": "https://api.spotify.com/v1/albums/4RXn64FAasCSt8Tsyx8iMU",
          "id": "4RXn64FAasCSt8Tsyx8iMU",
          "images": [
            {
              "height": 640,
              "url": "https://i.scdn.co/image/ab67616d0000b2734ae9082326b157fea7c7ead9",
              "width": 640
            },
            {
              "height": 300,
              "url": "https://i.scdn.co/image/ab67616d00001e024ae9082326b157fea7c7ead9",
              "width": 300
            },
            {
              "height": 64,
              "url": "https://i.scdn.co/image/ab67616d000048514ae9082326b157fea7c7ead9",
              "width": 64
            }
          ],
          "name": "อย่าเป็นฉันเลย Tyrion",
          "release_date": "2020-12-04",
          "release_date_precision": "day",
          "total_tracks": 1,
          "type": "album",
          "uri": "spotify:album:4RXn64FAasCSt8Tsyx8iMU"
        },
        "artists": [
          {
            "external_urls": {
              "spotify": "https://open.spotify.com/artist/7lhxw2OpjLMGTrlUobUN3F"
            },
            "href": "https://api.spotify.com/v1/artists/7lhxw2OpjLMGTrlUobUN3F",
            "id": "7lhxw2OpjLMGTrlUobUN3F",
            "name": "Uncle Ben",
            "type": "artist",
            "uri": "spotify:artist:7lhxw2OpjLMGTrlUobUN3F"
          }
        ],
        "available_markets": [
          "AD",
          "AE",
          "AG",
          "AL",
          "AM",
          "AO",
          "AR",
          "AT",
          "AU",
          "AZ",
          "BA",
          "BB",
          "BD",
          "BE",
          "BF",
          "BG",
          "BH",
          "BI",
          "BJ",
          "BN",
          "BO",
          "BR",
          "BS",
          "BT",
          "BW",
          "BY",
          "BZ",
          "CA",
          "CD",
          "CG",
          "CH",
          "CI",
          "CL",
          "CM",
          "CO",
          "CR",
          "CV",
          "CW",
          "CY",
          "CZ",
          "DE",
          "DJ",
          "DK",
          "DM",
          "DO",
          "DZ",
          "EC",
          "EE",
          "EG",
          "ES",
          "FI",
          "FJ",
          "FM",
          "FR",
          "GA",
          "GB",
          "GD",
          "GE",
          "GH",
          "GM",
          "GN",
          "GQ",
          "GR",
          "GT",
          "GW",
          "GY",
          "HK",
          "HN",
          "HR",
          "HT",
          "HU",
          "ID",
          "IE",
          "IL",
          "IN",
          "IQ",
          "IS",
          "IT",
          "JM",
          "JO",
          "JP",
          "KE",
          "KG",
          "KH",
          "KI",
          "KM",
          "KN",
          "KR",
          "KW",
          "KZ",
          "LA",
          "LB",
          "LC",
          "LI",
          "LK",
          "LR",
          "LS",
          "LT",
          "LU",
          "LV",
          "LY",
          "MA",
          "MC",
          "MD",
          "ME",
          "MG",
          "MH",
          "MK",
          "ML",
          "MN",
          "MO",
          "MR",
          "MT",
          "MU",
          "MV",
          "MW",
          "MX",
          "MY",
          "MZ",
          "NA",
          "NE",
          "NG",
          "NI",
          "NL",
          "NO",
          "NP",
          "NR",
          "NZ",
          "OM",
          "PA",
          "PE",
          "PG",
          "PH",
          "PK",
          "PL",
          "PS",
          "PT",
          "PW",
          "PY",
          "QA",
          "RO",
          "RS",
          "RW",
          "SA",
          "SB",
          "SC",
          "SE",
          "SG",
          "SI",
          "SK",
          "SL",
          "SM",
          "SN",
          "SR",
          "ST",
          "SV",
          "SZ",
          "TD",
          "TG",
          "TH",
          "TJ",
          "TL",
          "TN",
          "TO",
          "TR",
          "TT",
          "TV",
          "TW",
          "TZ",
          "UA",
          "UG",
          "US",
          "UY",
          "UZ",
          "VC",
          "VE",
          "VN",
          "VU",
          "WS",
          "XK",
          "ZA",
          "ZM",
          "ZW"
        ],
        "disc_number": 1,
        "duration_ms": 391218,
        "explicit": false,
        "external_ids": {
          "isrc": "THMOB2010261"
        },
        "external_urls": {
          "spotify": "https://open.spotify.com/track/1khnGTGPtxEM6hczBQeC99"
        },
        "href": "https://api.spotify.com/v1/tracks/1khnGTGPtxEM6hczBQeC99",
        "id": "1khnGTGPtxEM6hczBQeC99",
        "is_local": false,
        "name": "อย่าเป็นฉันเลย Tyrion",
        "popularity": 48,
        "preview_url": "https://p.scdn.co/mp3-preview/07dc9d0e4efd27bdab929de71e697593b7878aca?cid=d91479fbfab04b6b84bc68559d2f97d2",
        "track_number": 1,
        "type": "track",
        "uri": "spotify:track:1khnGTGPtxEM6hczBQeC99"
      },
      "played_at": "2022-12-02T04:06:57.231Z",
      "context": {
        "external_urls": {
          "spotify": "https://open.spotify.com/playlist/6PWn5SZO1bJtmg6OJvdCe4"
        },
        "href": "https://api.spotify.com/v1/playlists/6PWn5SZO1bJtmg6OJvdCe4",
        "type": "playlist",
        "uri": "spotify:playlist:6PWn5SZO1bJtmg6OJvdCe4"
      }
    },
    {
      "track": {
        "album": {
          "album_type": "single",
          "artists": [
            {
              "external_urls": {
                "spotify": "https://open.spotify.com/artist/3vHLiSEszIgPRLxivAPHO9"
              },
              "href": "https://api.spotify.com/v1/artists/3vHLiSEszIgPRLxivAPHO9",
              "id": "3vHLiSEszIgPRLxivAPHO9",
              "name": "Laika",
              "type": "artist",
              "uri": "spotify:artist:3vHLiSEszIgPRLxivAPHO9"
            }
          ],
          "available_markets": [
            "AD",
            "AE",
            "AG",
            "AL",
            "AM",
            "AO",
            "AR",
            "AT",
            "AU",
            "AZ",
            "BA",
            "BB",
            "BD",
            "BE",
            "BF",
            "BG",
            "BH",
            "BI",
            "BJ",
            "BN",
            "BO",
            "BR",
            "BS",
            "BT",
            "BW",
            "BY",
            "BZ",
            "CA",
            "CD",
            "CG",
            "CH",
            "CI",
            "CL",
            "CM",
            "CO",
            "CR",
            "CV",
            "CW",
            "CY",
            "CZ",
            "DE",
            "DJ",
            "DK",
            "DM",
            "DO",
            "DZ",
            "EC",
            "EE",
            "EG",
            "ES",
            "FI",
            "FJ",
            "FM",
            "FR",
            "GA",
            "GB",
            "GD",
            "GE",
            "GH",
            "GM",
            "GN",
            "GQ",
            "GR",
            "GT",
            "GW",
            "GY",
            "HK",
            "HN",
            "HR",
            "HT",
            "HU",
            "ID",
            "IE",
            "IL",
            "IN",
            "IQ",
            "IS",
            "IT",
            "JM",
            "JO",
            "JP",
            "KE",
            "KG",
            "KH",
            "KI",
            "KM",
            "KN",
            "KR",
            "KW",
            "KZ",
            "LA",
            "LB",
            "LC",
            "LI",
            "LK",
            "LR",
            "LS",
            "LT",
            "LU",
            "LV",
            "LY",
            "MA",
            "MC",
            "MD",
            "ME",
            "MG",
            "MH",
            "MK",
            "ML",
            "MN",
            "MO",
            "MR",
            "MT",
            "MU",
            "MV",
            "MW",
            "MX",
            "MY",
            "MZ",
            "NA",
            "NE",
            "NG",
            "NI",
            "NL",
            "NO",
            "NP",
            "NR",
            "NZ",
            "OM",
            "PA",
            "PE",
            "PG",
            "PH",
            "PK",
            "PL",
            "PS",
            "PT",
            "PW",
            "PY",
            "QA",
            "RO",
            "RS",
            "RW",
            "SA",
            "SB",
            "SC",
            "SE",
            "SG",
            "SI",
            "SK",
            "SL",
            "SM",
            "SN",
            "SR",
            "ST",
            "SV",
            "SZ",
            "TD",
            "TG",
            "TH",
            "TJ",
            "TL",
            "TN",
            "TO",
            "TR",
            "TT",
            "TV",
            "TW",
            "TZ",
            "UA",
            "UG",
            "US",
            "UY",
            "UZ",
            "VC",
            "VE",
            "VN",
            "VU",
            "WS",
            "XK",
            "ZA",
            "ZM",
            "ZW"
          ],
          "external_urls": {
            "spotify": "https://open.spotify.com/album/6Pp73acZe8TfK1nbG4LM0i"
          },
          "href": "https://api.spotify.com/v1/albums/6Pp73acZe8TfK1nbG4LM0i",
          "id": "6Pp73acZe8TfK1nbG4LM0i",
          "images": [
            {
              "height": 640,
              "url": "https://i.scdn.co/image/ab67616d0000b2739f449cb3ba75390c0f25af33",
              "width": 640
            },
            {
              "height": 300,
              "url": "https://i.scdn.co/image/ab67616d00001e029f449cb3ba75390c0f25af33",
              "width": 300
            },
            {
              "height": 64,
              "url": "https://i.scdn.co/image/ab67616d000048519f449cb3ba75390c0f25af33",
              "width": 64
            }
          ],
          "name": "รอยแผล",
          "release_date": "2018-10-19",
          "release_date_precision": "day",
          "total_tracks": 1,
          "type": "album",
          "uri": "spotify:album:6Pp73acZe8TfK1nbG4LM0i"
        },
        "artists": [
          {
            "external_urls": {
              "spotify": "https://open.spotify.com/artist/3vHLiSEszIgPRLxivAPHO9"
            },
            "href": "https://api.spotify.com/v1/artists/3vHLiSEszIgPRLxivAPHO9",
            "id": "3vHLiSEszIgPRLxivAPHO9",
            "name": "Laika",
            "type": "artist",
            "uri": "spotify:artist:3vHLiSEszIgPRLxivAPHO9"
          }
        ],
        "available_markets": [
          "AD",
          "AE",
          "AG",
          "AL",
          "AM",
          "AO",
          "AR",
          "AT",
          "AU",
          "AZ",
          "BA",
          "BB",
          "BD",
          "BE",
          "BF",
          "BG",
          "BH",
          "BI",
          "BJ",
          "BN",
          "BO",
          "BR",
          "BS",
          "BT",
          "BW",
          "BY",
          "BZ",
          "CA",
          "CD",
          "CG",
          "CH",
          "CI",
          "CL",
          "CM",
          "CO",
          "CR",
          "CV",
          "CW",
          "CY",
          "CZ",
          "DE",
          "DJ",
          "DK",
          "DM",
          "DO",
          "DZ",
          "EC",
          "EE",
          "EG",
          "ES",
          "FI",
          "FJ",
          "FM",
          "FR",
          "GA",
          "GB",
          "GD",
          "GE",
          "GH",
          "GM",
          "GN",
          "GQ",
          "GR",
          "GT",
          "GW",
          "GY",
          "HK",
          "HN",
          "HR",
          "HT",
          "HU",
          "ID",
          "IE",
          "IL",
          "IN",
          "IQ",
          "IS",
          "IT",
          "JM",
          "JO",
          "JP",
          "KE",
          "KG",
          "KH",
          "KI",
          "KM",
          "KN",
          "KR",
          "KW",
          "KZ",
          "LA",
          "LB",
          "LC",
          "LI",
          "LK",
          "LR",
          "LS",
          "LT",
          "LU",
          "LV",
          "LY",
          "MA",
          "MC",
          "MD",
          "ME",
          "MG",
          "MH",
          "MK",
          "ML",
          "MN",
          "MO",
          "MR",
          "MT",
          "MU",
          "MV",
          "MW",
          "MX",
          "MY",
          "MZ",
          "NA",
          "NE",
          "NG",
          "NI",
          "NL",
          "NO",
          "NP",
          "NR",
          "NZ",
          "OM",
          "PA",
          "PE",
          "PG",
          "PH",
          "PK",
          "PL",
          "PS",
          "PT",
          "PW",
          "PY",
          "QA",
          "RO",
          "RS",
          "RW",
          "SA",
          "SB",
          "SC",
          "SE",
          "SG",
          "SI",
          "SK",
          "SL",
          "SM",
          "SN",
          "SR",
          "ST",
          "SV",
          "SZ",
          "TD",
          "TG",
          "TH",
          "TJ",
          "TL",
          "TN",
          "TO",
          "TR",
          "TT",
          "TV",
          "TW",
          "TZ",
          "UA",
          "UG",
          "US",
          "UY",
          "UZ",
          "VC",
          "VE",
          "VN",
          "VU",
          "WS",
          "XK",
          "ZA",
          "ZM",
          "ZW"
        ],
        "disc_number": 1,
        "duration_ms": 264225,
        "explicit": false,
        "external_ids": {
          "isrc": "THMOB1805068"
        },
        "external_urls": {
          "spotify": "https://open.spotify.com/track/5mdStbB6eQ3psN08RsQkOa"
        },
        "href": "https://api.spotify.com/v1/tracks/5mdStbB6eQ3psN08RsQkOa",
        "id": "5mdStbB6eQ3psN08RsQkOa",
        "is_local": false,
        "name": "รอยแผล",
        "popularity": 37,
        "preview_url": "https://p.scdn.co/mp3-preview/20549d898c50ea57f68973a2a74de49c23fb928f?cid=d91479fbfab04b6b84bc68559d2f97d2",
        "track_number": 1,
        "type": "track",
        "uri": "spotify:track:5mdStbB6eQ3psN08RsQkOa"
      },
      "played_at": "2022-12-02T05:22:57.917Z",
      "context": {
        "external_urls": {
          "spotify": "https://open.spotify.com/playlist/6PWn5SZO1bJtmg6OJvdCe4"
        },
        "href": "https://api.spotify.com/v1/playlists/6PWn5SZO1bJtmg6OJvdCe4",
        "type": "playlist",
        "uri": "spotify:playlist:6PWn5SZO1bJtmg6OJvdCe4"
      }
    },
    {
      "track": {
        "album": {
          "album_type": "single",
          "artists": [
            {
              "external_urls": {
                "spotify": "https://open.spotify.com/artist/3u45DFB1kjVXKwE14FKXCo"
              },
              "href": "https://api.spotify.com/v1/artists/3u45DFB1kjVXKwE14FKXCo",
              "id": "3u45DFB1kjVXKwE14FKXCo",
              "name": "Blackbeans",
              "type": "artist",
              "uri": "spotify:artist:3u45DFB1kjVXKwE14FKXCo"
            }
          ],
          "available_markets": [
            "AD",
            "AE",
            "AG",
            "AL",
            "AM",
            "AO",
            "AR",
            "AT",
            "AU",
            "AZ",
            "BA",
            "BB",
            "BD",
            "BE",
            "BF",
            "BG",
            "BH",
            "BI",
            "BJ",
            "BN",
            "BO",
            "BR",
            "BS",
            "BT",
            "BW",
            "BY",
            "BZ",
            "CA",
            "CD",
            "CG",
            "CH",
            "CI",
            "CL",
            "CM",
            "CO",
            "CR",
            "CV",
            "CW",
            "CY",
            "CZ",
            "DE",
            "DJ",
            "DK",
            "DM",
            "DO",
            "DZ",
            "EC",
            "EE",
            "EG",
            "ES",
            "FI",
            "FJ",
            "FM",
            "FR",
            "GA",
            "GB",
            "GD",
            "GE",
            "GH",
            "GM",
            "GN",
            "GQ",
            "GR",
            "GT",
            "GW",
            "GY",
            "HK",
            "HN",
            "HR",
            "HT",
            "HU",
            "ID",
            "IE",
            "IL",
            "IN",
            "IQ",
            "IS",
            "IT",
            "JM",
            "JO",
            "JP",
            "KE",
            "KG",
            "KH",
            "KI",
            "KM",
            "KN",
            "KR",
            "KW",
            "KZ",
            "LA",
            "LB",
            "LC",
            "LI",
            "LK",
            "LR",
            "LS",
            "LT",
            "LU",
            "LV",
            "LY",
            "MA",
            "MC",
            "MD",
            "ME",
            "MG",
            "MH",
            "MK",
            "ML",
            "MN",
            "MO",
            "MR",
            "MT",
            "MU",
            "MV",
            "MW",
            "MX",
            "MY",
            "MZ",
            "NA",
            "NE",
            "NG",
            "NI",
            "NL",
            "NO",
            "NP",
            "NR",
            "NZ",
            "OM",
            "PA",
            "PE",
            "PG",
            "PH",
            "PK",
            "PL",
            "PS",
            "PT",
            "PW",
            "PY",
            "QA",
            "RO",
            "RS",
            "RW",
            "SA",
            "SB",
            "SC",
            "SE",
            "SG",
            "SI",
            "SK",
            "SL",
            "SM",
            "SN",
            "SR",
            "ST",
            "SV",
            "SZ",
            "TD",
            "TG",
            "TH",
            "TJ",
            "TL",
            "TN",
            "TO",
            "TR",
            "TT",
            "TV",
            "TW",
            "TZ",
            "UA",
            "UG",
            "US",
            "UY",
            "UZ",
            "VC",
            "VE",
            "VN",
            "VU",
            "WS",
            "XK",
            "ZA",
            "ZM",
            "ZW"
          ],
          "external_urls": {
            "spotify": "https://open.spotify.com/album/27iuwT6bnRrZ2WYHz8vDaT"
          },
          "href": "https://api.spotify.com/v1/albums/27iuwT6bnRrZ2WYHz8vDaT",
          "id": "27iuwT6bnRrZ2WYHz8vDaT",
          "images": [
            {
              "height": 640,
              "url": "https://i.scdn.co/image/ab67616d0000b273072e6ec06bc7c11d9c0ae8dc",
              "width": 640
            },
            {
              "height": 300,
              "url": "https://i.scdn.co/image/ab67616d00001e02072e6ec06bc7c11d9c0ae8dc",
              "width": 300
            },
            {
              "height": 64,
              "url": "https://i.scdn.co/image/ab67616d00004851072e6ec06bc7c11d9c0ae8dc",
              "width": 64
            }
          ],
          "name": "Wish",
          "release_date": "2019-07-05",
          "release_date_precision": "day",
          "total_tracks": 1,
          "type": "album",
          "uri": "spotify:album:27iuwT6bnRrZ2WYHz8vDaT"
        },
        "artists": [
          {
            "external_urls": {
              "spotify": "https://open.spotify.com/artist/3u45DFB1kjVXKwE14FKXCo"
            },
            "href": "https://api.spotify.com/v1/artists/3u45DFB1kjVXKwE14FKXCo",
            "id": "3u45DFB1kjVXKwE14FKXCo",
            "name": "Blackbeans",
            "type": "artist",
            "uri": "spotify:artist:3u45DFB1kjVXKwE14FKXCo"
          }
        ],
        "available_markets": [
          "AD",
          "AE",
          "AG",
          "AL",
          "AM",
          "AO",
          "AR",
          "AT",
          "AU",
          "AZ",
          "BA",
          "BB",
          "BD",
          "BE",
          "BF",
          "BG",
          "BH",
          "BI",
          "BJ",
          "BN",
          "BO",
          "BR",
          "BS",
          "BT",
          "BW",
          "BY",
          "BZ",
          "CA",
          "CD",
          "CG",
          "CH",
          "CI",
          "CL",
          "CM",
          "CO",
          "CR",
          "CV",
          "CW",
          "CY",
          "CZ",
          "DE",
          "DJ",
          "DK",
          "DM",
          "DO",
          "DZ",
          "EC",
          "EE",
          "EG",
          "ES",
          "FI",
          "FJ",
          "FM",
          "FR",
          "GA",
          "GB",
          "GD",
          "GE",
          "GH",
          "GM",
          "GN",
          "GQ",
          "GR",
          "GT",
          "GW",
          "GY",
          "HK",
          "HN",
          "HR",
          "HT",
          "HU",
          "ID",
          "IE",
          "IL",
          "IN",
          "IQ",
          "IS",
          "IT",
          "JM",
          "JO",
          "JP",
          "KE",
          "KG",
          "KH",
          "KI",
          "KM",
          "KN",
          "KR",
          "KW",
          "KZ",
          "LA",
          "LB",
          "LC",
          "LI",
          "LK",
          "LR",
          "LS",
          "LT",
          "LU",
          "LV",
          "LY",
          "MA",
          "MC",
          "MD",
          "ME",
          "MG",
          "MH",
          "MK",
          "ML",
          "MN",
          "MO",
          "MR",
          "MT",
          "MU",
          "MV",
          "MW",
          "MX",
          "MY",
          "MZ",
          "NA",
          "NE",
          "NG",
          "NI",
          "NL",
          "NO",
          "NP",
          "NR",
          "NZ",
          "OM",
          "PA",
          "PE",
          "PG",
          "PH",
          "PK",
          "PL",
          "PS",
          "PT",
          "PW",
          "PY",
          "QA",
          "RO",
          "RS",
          "RW",
          "SA",
          "SB",
          "SC",
          "SE",
          "SG",
          "SI",
          "SK",
          "SL",
          "SM",
          "SN",
          "SR",
          "ST",
          "SV",
          "SZ",
          "TD",
          "TG",
          "TH",
          "TJ",
          "TL",
          "TN",
          "TO",
          "TR",
          "TT",
          "TV",
          "TW",
          "TZ",
          "UA",
          "UG",
          "US",
          "UY",
          "UZ",
          "VC",
          "VE",
          "VN",
          "VU",
          "WS",
          "XK",
          "ZA",
          "ZM",
          "ZW"
        ],
        "disc_number": 1,
        "duration_ms": 271764,
        "explicit": false,
        "external_ids": {
          "isrc": "THMOB1906527"
        },
        "external_urls": {
          "spotify": "https://open.spotify.com/track/7uvyBv9i8OEk8Jc2MHzaoB"
        },
        "href": "https://api.spotify.com/v1/tracks/7uvyBv9i8OEk8Jc2MHzaoB",
        "id": "7uvyBv9i8OEk8Jc2MHzaoB",
        "is_local": false,
        "name": "Wish",
        "popularity": 45,
        "preview_url": "https://p.scdn.co/mp3-preview/e1790743ff40bd69773e84d504e9e93d78ce3086?cid=d91479fbfab04b6b84bc68559d2f97d2",
        "track_number": 1,
        "type": "track",
        "uri": "spotify:track:7uvyBv9i8OEk8Jc2MHzaoB"
      },
      "played_at": "2022-12-02T05:24:00.832Z",
      "context": {
        "type": "playlist",
        "external_urls": {
          "spotify": "https://open.spotify.com/playlist/6PWn5SZO1bJtmg6OJvdCe4"
        },
        "href": "https://api.spotify.com/v1/playlists/6PWn5SZO1bJtmg6OJvdCe4",
        "uri": "spotify:playlist:6PWn5SZO1bJtmg6OJvdCe4"
      }
    },
    {
      "track": {
        "album": {
          "album_type": "album",
          "artists": [
            {
              "external_urls": {
                "spotify": "https://open.spotify.com/artist/1m3zDfkzk9x6eUMjMM1e1f"
              },
              "href": "https://api.spotify.com/v1/artists/1m3zDfkzk9x6eUMjMM1e1f",
              "id": "1m3zDfkzk9x6eUMjMM1e1f",
              "name": "Kokomo",
              "type": "artist",
              "uri": "spotify:artist:1m3zDfkzk9x6eUMjMM1e1f"
            }
          ],
          "available_markets": [
            "AD",
            "AE",
            "AG",
            "AL",
            "AM",
            "AO",
            "AR",
            "AT",
            "AU",
            "AZ",
            "BA",
            "BB",
            "BD",
            "BE",
            "BF",
            "BG",
            "BH",
            "BI",
            "BJ",
            "BN",
            "BO",
            "BR",
            "BS",
            "BT",
            "BW",
            "BY",
            "BZ",
            "CA",
            "CD",
            "CG",
            "CH",
            "CI",
            "CL",
            "CM",
            "CO",
            "CR",
            "CV",
            "CW",
            "CY",
            "CZ",
            "DE",
            "DJ",
            "DK",
            "DM",
            "DO",
            "DZ",
            "EC",
            "EE",
            "EG",
            "ES",
            "FI",
            "FJ",
            "FM",
            "FR",
            "GA",
            "GB",
            "GD",
            "GE",
            "GH",
            "GM",
            "GN",
            "GQ",
            "GR",
            "GT",
            "GW",
            "GY",
            "HK",
            "HN",
            "HR",
            "HT",
            "HU",
            "ID",
            "IE",
            "IL",
            "IN",
            "IQ",
            "IS",
            "IT",
            "JM",
            "JO",
            "JP",
            "KE",
            "KG",
            "KH",
            "KI",
            "KM",
            "KN",
            "KR",
            "KW",
            "KZ",
            "LA",
            "LB",
            "LC",
            "LI",
            "LK",
            "LR",
            "LS",
            "LT",
            "LU",
            "LV",
            "LY",
            "MA",
            "MC",
            "MD",
            "ME",
            "MG",
            "MH",
            "MK",
            "ML",
            "MN",
            "MO",
            "MR",
            "MT",
            "MU",
            "MV",
            "MW",
            "MX",
            "MY",
            "MZ",
            "NA",
            "NE",
            "NG",
            "NI",
            "NL",
            "NO",
            "NP",
            "NR",
            "NZ",
            "OM",
            "PA",
            "PE",
            "PG",
            "PH",
            "PK",
            "PL",
            "PS",
            "PT",
            "PW",
            "PY",
            "QA",
            "RO",
            "RS",
            "RW",
            "SA",
            "SB",
            "SC",
            "SE",
            "SG",
            "SI",
            "SK",
            "SL",
            "SM",
            "SN",
            "SR",
            "ST",
            "SV",
            "SZ",
            "TD",
            "TG",
            "TH",
            "TJ",
            "TL",
            "TN",
            "TO",
            "TR",
            "TT",
            "TV",
            "TW",
            "TZ",
            "UA",
            "UG",
            "US",
            "UY",
            "UZ",
            "VC",
            "VE",
            "VN",
            "VU",
            "WS",
            "XK",
            "ZA",
            "ZM",
            "ZW"
          ],
          "external_urls": {
            "spotify": "https://open.spotify.com/album/3e2mNMzLCLYpbD9fd5zJck"
          },
          "href": "https://api.spotify.com/v1/albums/3e2mNMzLCLYpbD9fd5zJck",
          "id": "3e2mNMzLCLYpbD9fd5zJck",
          "images": [
            {
              "height": 640,
              "url": "https://i.scdn.co/image/ab67616d0000b273dc4c6f8e8c415e7240832c4a",
              "width": 640
            },
            {
              "height": 300,
              "url": "https://i.scdn.co/image/ab67616d00001e02dc4c6f8e8c415e7240832c4a",
              "width": 300
            },
            {
              "height": 64,
              "url": "https://i.scdn.co/image/ab67616d00004851dc4c6f8e8c415e7240832c4a",
              "width": 64
            }
          ],
          "name": "If Wolves",
          "release_date": "2011-04-23",
          "release_date_precision": "day",
          "total_tracks": 6,
          "type": "album",
          "uri": "spotify:album:3e2mNMzLCLYpbD9fd5zJck"
        },
        "artists": [
          {
            "external_urls": {
              "spotify": "https://open.spotify.com/artist/1m3zDfkzk9x6eUMjMM1e1f"
            },
            "href": "https://api.spotify.com/v1/artists/1m3zDfkzk9x6eUMjMM1e1f",
            "id": "1m3zDfkzk9x6eUMjMM1e1f",
            "name": "Kokomo",
            "type": "artist",
            "uri": "spotify:artist:1m3zDfkzk9x6eUMjMM1e1f"
          }
        ],
        "available_markets": [
          "AD",
          "AE",
          "AG",
          "AL",
          "AM",
          "AO",
          "AR",
          "AT",
          "AU",
          "AZ",
          "BA",
          "BB",
          "BD",
          "BE",
          "BF",
          "BG",
          "BH",
          "BI",
          "BJ",
          "BN",
          "BO",
          "BR",
          "BS",
          "BT",
          "BW",
          "BY",
          "BZ",
          "CA",
          "CD",
          "CG",
          "CH",
          "CI",
          "CL",
          "CM",
          "CO",
          "CR",
          "CV",
          "CW",
          "CY",
          "CZ",
          "DE",
          "DJ",
          "DK",
          "DM",
          "DO",
          "DZ",
          "EC",
          "EE",
          "EG",
          "ES",
          "FI",
          "FJ",
          "FM",
          "FR",
          "GA",
          "GB",
          "GD",
          "GE",
          "GH",
          "GM",
          "GN",
          "GQ",
          "GR",
          "GT",
          "GW",
          "GY",
          "HK",
          "HN",
          "HR",
          "HT",
          "HU",
          "ID",
          "IE",
          "IL",
          "IN",
          "IQ",
          "IS",
          "IT",
          "JM",
          "JO",
          "JP",
          "KE",
          "KG",
          "KH",
          "KI",
          "KM",
          "KN",
          "KR",
          "KW",
          "KZ",
          "LA",
          "LB",
          "LC",
          "LI",
          "LK",
          "LR",
          "LS",
          "LT",
          "LU",
          "LV",
          "LY",
          "MA",
          "MC",
          "MD",
          "ME",
          "MG",
          "MH",
          "MK",
          "ML",
          "MN",
          "MO",
          "MR",
          "MT",
          "MU",
          "MV",
          "MW",
          "MX",
          "MY",
          "MZ",
          "NA",
          "NE",
          "NG",
          "NI",
          "NL",
          "NO",
          "NP",
          "NR",
          "NZ",
          "OM",
          "PA",
          "PE",
          "PG",
          "PH",
          "PK",
          "PL",
          "PS",
          "PT",
          "PW",
          "PY",
          "QA",
          "RO",
          "RS",
          "RW",
          "SA",
          "SB",
          "SC",
          "SE",
          "SG",
          "SI",
          "SK",
          "SL",
          "SM",
          "SN",
          "SR",
          "ST",
          "SV",
          "SZ",
          "TD",
          "TG",
          "TH",
          "TJ",
          "TL",
          "TN",
          "TO",
          "TR",
          "TT",
          "TV",
          "TW",
          "TZ",
          "UA",
          "UG",
          "US",
          "UY",
          "UZ",
          "VC",
          "VE",
          "VN",
          "VU",
          "WS",
          "XK",
          "ZA",
          "ZM",
          "ZW"
        ],
        "disc_number": 1,
        "duration_ms": 531466,
        "explicit": false,
        "external_ids": {
          "isrc": "ushm21289159"
        },
        "external_urls": {
          "spotify": "https://open.spotify.com/track/3i9WMoyFW4fz7FbKlokDoX"
        },
        "href": "https://api.spotify.com/v1/tracks/3i9WMoyFW4fz7FbKlokDoX",
        "id": "3i9WMoyFW4fz7FbKlokDoX",
        "is_local": false,
        "name": "Fuchs",
        "popularity": 3,
        "preview_url": "https://p.scdn.co/mp3-preview/3c50ab9a4f1687b77e66d4a712db7ee174842785?cid=d91479fbfab04b6b84bc68559d2f97d2",
        "track_number": 6,
        "type": "track",
        "uri": "spotify:track:3i9WMoyFW4fz7FbKlokDoX"
      },
      "played_at": "2022-12-02T09:01:20.864Z",
      "context": null
    },
    {
      "track": {
        "album": {
          "album_type": "album",
          "artists": [
            {
              "external_urls": {
                "spotify": "https://open.spotify.com/artist/1m3zDfkzk9x6eUMjMM1e1f"
              },
              "href": "https://api.spotify.com/v1/artists/1m3zDfkzk9x6eUMjMM1e1f",
              "id": "1m3zDfkzk9x6eUMjMM1e1f",
              "name": "Kokomo",
              "type": "artist",
              "uri": "spotify:artist:1m3zDfkzk9x6eUMjMM1e1f"
            }
          ],
          "available_markets": [
            "AD",
            "AE",
            "AG",
            "AL",
            "AM",
            "AO",
            "AR",
            "AT",
            "AU",
            "AZ",
            "BA",
            "BB",
            "BD",
            "BE",
            "BF",
            "BG",
            "BH",
            "BI",
            "BJ",
            "BN",
            "BO",
            "BR",
            "BS",
            "BT",
            "BW",
            "BY",
            "BZ",
            "CA",
            "CD",
            "CG",
            "CH",
            "CI",
            "CL",
            "CM",
            "CO",
            "CR",
            "CV",
            "CW",
            "CY",
            "CZ",
            "DE",
            "DJ",
            "DK",
            "DM",
            "DO",
            "DZ",
            "EC",
            "EE",
            "EG",
            "ES",
            "FI",
            "FJ",
            "FM",
            "FR",
            "GA",
            "GB",
            "GD",
            "GE",
            "GH",
            "GM",
            "GN",
            "GQ",
            "GR",
            "GT",
            "GW",
            "GY",
            "HK",
            "HN",
            "HR",
            "HT",
            "HU",
            "ID",
            "IE",
            "IL",
            "IN",
            "IQ",
            "IS",
            "IT",
            "JM",
            "JO",
            "JP",
            "KE",
            "KG",
            "KH",
            "KI",
            "KM",
            "KN",
            "KR",
            "KW",
            "KZ",
            "LA",
            "LB",
            "LC",
            "LI",
            "LK",
            "LR",
            "LS",
            "LT",
            "LU",
            "LV",
            "LY",
            "MA",
            "MC",
            "MD",
            "ME",
            "MG",
            "MH",
            "MK",
            "ML",
            "MN",
            "MO",
            "MR",
            "MT",
            "MU",
            "MV",
            "MW",
            "MX",
            "MY",
            "MZ",
            "NA",
            "NE",
            "NG",
            "NI",
            "NL",
            "NO",
            "NP",
            "NR",
            "NZ",
            "OM",
            "PA",
            "PE",
            "PG",
            "PH",
            "PK",
            "PL",
            "PS",
            "PT",
            "PW",
            "PY",
            "QA",
            "RO",
            "RS",
            "RW",
            "SA",
            "SB",
            "SC",
            "SE",
            "SG",
            "SI",
            "SK",
            "SL",
            "SM",
            "SN",
            "SR",
            "ST",
            "SV",
            "SZ",
            "TD",
            "TG",
            "TH",
            "TJ",
            "TL",
            "TN",
            "TO",
            "TR",
            "TT",
            "TV",
            "TW",
            "TZ",
            "UA",
            "UG",
            "US",
            "UY",
            "UZ",
            "VC",
            "VE",
            "VN",
            "VU",
            "WS",
            "XK",
            "ZA",
            "ZM",
            "ZW"
          ],
          "external_urls": {
            "spotify": "https://open.spotify.com/album/3e2mNMzLCLYpbD9fd5zJck"
          },
          "href": "https://api.spotify.com/v1/albums/3e2mNMzLCLYpbD9fd5zJck",
          "id": "3e2mNMzLCLYpbD9fd5zJck",
          "images": [
            {
              "height": 640,
              "url": "https://i.scdn.co/image/ab67616d0000b273dc4c6f8e8c415e7240832c4a",
              "width": 640
            },
            {
              "height": 300,
              "url": "https://i.scdn.co/image/ab67616d00001e02dc4c6f8e8c415e7240832c4a",
              "width": 300
            },
            {
              "height": 64,
              "url": "https://i.scdn.co/image/ab67616d00004851dc4c6f8e8c415e7240832c4a",
              "width": 64
            }
          ],
          "name": "If Wolves",
          "release_date": "2011-04-23",
          "release_date_precision": "day",
          "total_tracks": 6,
          "type": "album",
          "uri": "spotify:album:3e2mNMzLCLYpbD9fd5zJck"
        },
        "artists": [
          {
            "external_urls": {
              "spotify": "https://open.spotify.com/artist/1m3zDfkzk9x6eUMjMM1e1f"
            },
            "href": "https://api.spotify.com/v1/artists/1m3zDfkzk9x6eUMjMM1e1f",
            "id": "1m3zDfkzk9x6eUMjMM1e1f",
            "name": "Kokomo",
            "type": "artist",
            "uri": "spotify:artist:1m3zDfkzk9x6eUMjMM1e1f"
          }
        ],
        "available_markets": [
          "AD",
          "AE",
          "AG",
          "AL",
          "AM",
          "AO",
          "AR",
          "AT",
          "AU",
          "AZ",
          "BA",
          "BB",
          "BD",
          "BE",
          "BF",
          "BG",
          "BH",
          "BI",
          "BJ",
          "BN",
          "BO",
          "BR",
          "BS",
          "BT",
          "BW",
          "BY",
          "BZ",
          "CA",
          "CD",
          "CG",
          "CH",
          "CI",
          "CL",
          "CM",
          "CO",
          "CR",
          "CV",
          "CW",
          "CY",
          "CZ",
          "DE",
          "DJ",
          "DK",
          "DM",
          "DO",
          "DZ",
          "EC",
          "EE",
          "EG",
          "ES",
          "FI",
          "FJ",
          "FM",
          "FR",
          "GA",
          "GB",
          "GD",
          "GE",
          "GH",
          "GM",
          "GN",
          "GQ",
          "GR",
          "GT",
          "GW",
          "GY",
          "HK",
          "HN",
          "HR",
          "HT",
          "HU",
          "ID",
          "IE",
          "IL",
          "IN",
          "IQ",
          "IS",
          "IT",
          "JM",
          "JO",
          "JP",
          "KE",
          "KG",
          "KH",
          "KI",
          "KM",
          "KN",
          "KR",
          "KW",
          "KZ",
          "LA",
          "LB",
          "LC",
          "LI",
          "LK",
          "LR",
          "LS",
          "LT",
          "LU",
          "LV",
          "LY",
          "MA",
          "MC",
          "MD",
          "ME",
          "MG",
          "MH",
          "MK",
          "ML",
          "MN",
          "MO",
          "MR",
          "MT",
          "MU",
          "MV",
          "MW",
          "MX",
          "MY",
          "MZ",
          "NA",
          "NE",
          "NG",
          "NI",
          "NL",
          "NO",
          "NP",
          "NR",
          "NZ",
          "OM",
          "PA",
          "PE",
          "PG",
          "PH",
          "PK",
          "PL",
          "PS",
          "PT",
          "PW",
          "PY",
          "QA",
          "RO",
          "RS",
          "RW",
          "SA",
          "SB",
          "SC",
          "SE",
          "SG",
          "SI",
          "SK",
          "SL",
          "SM",
          "SN",
          "SR",
          "ST",
          "SV",
          "SZ",
          "TD",
          "TG",
          "TH",
          "TJ",
          "TL",
          "TN",
          "TO",
          "TR",
          "TT",
          "TV",
          "TW",
          "TZ",
          "UA",
          "UG",
          "US",
          "UY",
          "UZ",
          "VC",
          "VE",
          "VN",
          "VU",
          "WS",
          "XK",
          "ZA",
          "ZM",
          "ZW"
        ],
        "disc_number": 1,
        "duration_ms": 531466,
        "explicit": false,
        "external_ids": {
          "isrc": "ushm21289159"
        },
        "external_urls": {
          "spotify": "https://open.spotify.com/track/3i9WMoyFW4fz7FbKlokDoX"
        },
        "href": "https://api.spotify.com/v1/tracks/3i9WMoyFW4fz7FbKlokDoX",
        "id": "3i9WMoyFW4fz7FbKlokDoX",
        "is_local": false,
        "name": "Fuchs",
        "popularity": 3,
        "preview_url": "https://p.scdn.co/mp3-preview/3c50ab9a4f1687b77e66d4a712db7ee174842785?cid=d91479fbfab04b6b84bc68559d2f97d2",
        "track_number": 6,
        "type": "track",
        "uri": "spotify:track:3i9WMoyFW4fz7FbKlokDoX"
      },
      "played_at": "2022-12-02T09:10:12.963Z",
      "context": null
    },
    {
      "track": {
        "album": {
          "album_type": "single",
          "artists": [
            {
              "external_urls": {
                "spotify": "https://open.spotify.com/artist/1e7K8jD3wRuQfnwDAOeGqe"
              },
              "href": "https://api.spotify.com/v1/artists/1e7K8jD3wRuQfnwDAOeGqe",
              "id": "1e7K8jD3wRuQfnwDAOeGqe",
              "name": "Fiji Blue",
              "type": "artist",
              "uri": "spotify:artist:1e7K8jD3wRuQfnwDAOeGqe"
            }
          ],
          "available_markets": [
            "AD",
            "AE",
            "AG",
            "AL",
            "AM",
            "AO",
            "AR",
            "AT",
            "AU",
            "AZ",
            "BA",
            "BB",
            "BD",
            "BE",
            "BF",
            "BG",
            "BH",
            "BI",
            "BJ",
            "BN",
            "BO",
            "BR",
            "BS",
            "BT",
            "BW",
            "BY",
            "BZ",
            "CA",
            "CD",
            "CG",
            "CH",
            "CI",
            "CL",
            "CM",
            "CO",
            "CR",
            "CV",
            "CW",
            "CY",
            "CZ",
            "DE",
            "DJ",
            "DK",
            "DM",
            "DO",
            "DZ",
            "EC",
            "EE",
            "EG",
            "ES",
            "FI",
            "FJ",
            "FM",
            "FR",
            "GA",
            "GB",
            "GD",
            "GE",
            "GH",
            "GM",
            "GN",
            "GQ",
            "GR",
            "GT",
            "GW",
            "GY",
            "HK",
            "HN",
            "HR",
            "HT",
            "HU",
            "ID",
            "IE",
            "IL",
            "IN",
            "IQ",
            "IS",
            "IT",
            "JM",
            "JO",
            "JP",
            "KE",
            "KG",
            "KH",
            "KI",
            "KM",
            "KN",
            "KR",
            "KW",
            "KZ",
            "LA",
            "LB",
            "LC",
            "LI",
            "LK",
            "LR",
            "LS",
            "LT",
            "LU",
            "LV",
            "LY",
            "MA",
            "MC",
            "MD",
            "ME",
            "MG",
            "MH",
            "MK",
            "ML",
            "MN",
            "MO",
            "MR",
            "MT",
            "MU",
            "MV",
            "MW",
            "MX",
            "MY",
            "MZ",
            "NA",
            "NE",
            "NG",
            "NI",
            "NL",
            "NO",
            "NP",
            "NR",
            "NZ",
            "OM",
            "PA",
            "PE",
            "PG",
            "PH",
            "PK",
            "PL",
            "PS",
            "PT",
            "PW",
            "PY",
            "QA",
            "RO",
            "RS",
            "RW",
            "SA",
            "SB",
            "SC",
            "SE",
            "SG",
            "SI",
            "SK",
            "SL",
            "SM",
            "SN",
            "SR",
            "ST",
            "SV",
            "SZ",
            "TD",
            "TG",
            "TH",
            "TJ",
            "TL",
            "TN",
            "TO",
            "TR",
            "TT",
            "TV",
            "TW",
            "TZ",
            "UA",
            "UG",
            "US",
            "UY",
            "UZ",
            "VC",
            "VE",
            "VN",
            "VU",
            "WS",
            "XK",
            "ZA",
            "ZM",
            "ZW"
          ],
          "external_urls": {
            "spotify": "https://open.spotify.com/album/3bTLu0LF1pBSZsZUDohta0"
          },
          "href": "https://api.spotify.com/v1/albums/3bTLu0LF1pBSZsZUDohta0",
          "id": "3bTLu0LF1pBSZsZUDohta0",
          "images": [
            {
              "height": 640,
              "url": "https://i.scdn.co/image/ab67616d0000b2736cee58caa91f712f58dd5e9c",
              "width": 640
            },
            {
              "height": 300,
              "url": "https://i.scdn.co/image/ab67616d00001e026cee58caa91f712f58dd5e9c",
              "width": 300
            },
            {
              "height": 64,
              "url": "https://i.scdn.co/image/ab67616d000048516cee58caa91f712f58dd5e9c",
              "width": 64
            }
          ],
          "name": "It Takes Two",
          "release_date": "2021-02-25",
          "release_date_precision": "day",
          "total_tracks": 1,
          "type": "album",
          "uri": "spotify:album:3bTLu0LF1pBSZsZUDohta0"
        },
        "artists": [
          {
            "external_urls": {
              "spotify": "https://open.spotify.com/artist/1e7K8jD3wRuQfnwDAOeGqe"
            },
            "href": "https://api.spotify.com/v1/artists/1e7K8jD3wRuQfnwDAOeGqe",
            "id": "1e7K8jD3wRuQfnwDAOeGqe",
            "name": "Fiji Blue",
            "type": "artist",
            "uri": "spotify:artist:1e7K8jD3wRuQfnwDAOeGqe"
          }
        ],
        "available_markets": [
          "AD",
          "AE",
          "AG",
          "AL",
          "AM",
          "AO",
          "AR",
          "AT",
          "AU",
          "AZ",
          "BA",
          "BB",
          "BD",
          "BE",
          "BF",
          "BG",
          "BH",
          "BI",
          "BJ",
          "BN",
          "BO",
          "BR",
          "BS",
          "BT",
          "BW",
          "BY",
          "BZ",
          "CA",
          "CD",
          "CG",
          "CH",
          "CI",
          "CL",
          "CM",
          "CO",
          "CR",
          "CV",
          "CW",
          "CY",
          "CZ",
          "DE",
          "DJ",
          "DK",
          "DM",
          "DO",
          "DZ",
          "EC",
          "EE",
          "EG",
          "ES",
          "FI",
          "FJ",
          "FM",
          "FR",
          "GA",
          "GB",
          "GD",
          "GE",
          "GH",
          "GM",
          "GN",
          "GQ",
          "GR",
          "GT",
          "GW",
          "GY",
          "HK",
          "HN",
          "HR",
          "HT",
          "HU",
          "ID",
          "IE",
          "IL",
          "IN",
          "IQ",
          "IS",
          "IT",
          "JM",
          "JO",
          "JP",
          "KE",
          "KG",
          "KH",
          "KI",
          "KM",
          "KN",
          "KR",
          "KW",
          "KZ",
          "LA",
          "LB",
          "LC",
          "LI",
          "LK",
          "LR",
          "LS",
          "LT",
          "LU",
          "LV",
          "LY",
          "MA",
          "MC",
          "MD",
          "ME",
          "MG",
          "MH",
          "MK",
          "ML",
          "MN",
          "MO",
          "MR",
          "MT",
          "MU",
          "MV",
          "MW",
          "MX",
          "MY",
          "MZ",
          "NA",
          "NE",
          "NG",
          "NI",
          "NL",
          "NO",
          "NP",
          "NR",
          "NZ",
          "OM",
          "PA",
          "PE",
          "PG",
          "PH",
          "PK",
          "PL",
          "PS",
          "PT",
          "PW",
          "PY",
          "QA",
          "RO",
          "RS",
          "RW",
          "SA",
          "SB",
          "SC",
          "SE",
          "SG",
          "SI",
          "SK",
          "SL",
          "SM",
          "SN",
          "SR",
          "ST",
          "SV",
          "SZ",
          "TD",
          "TG",
          "TH",
          "TJ",
          "TL",
          "TN",
          "TO",
          "TR",
          "TT",
          "TV",
          "TW",
          "TZ",
          "UA",
          "UG",
          "US",
          "UY",
          "UZ",
          "VC",
          "VE",
          "VN",
          "VU",
          "WS",
          "XK",
          "ZA",
          "ZM",
          "ZW"
        ],
        "disc_number": 1,
        "duration_ms": 159012,
        "explicit": false,
        "external_ids": {
          "isrc": "TCAFI2178857"
        },
        "external_urls": {
          "spotify": "https://open.spotify.com/track/5V7qLbZJNTwaEVbZADqofc"
        },
        "href": "https://api.spotify.com/v1/tracks/5V7qLbZJNTwaEVbZADqofc",
        "id": "5V7qLbZJNTwaEVbZADqofc",
        "is_local": false,
        "name": "It Takes Two",
        "popularity": 66,
        "preview_url": "https://p.scdn.co/mp3-preview/d52d227de370f4f7e989d794001f6e565a072458?cid=d91479fbfab04b6b84bc68559d2f97d2",
        "track_number": 1,
        "type": "track",
        "uri": "spotify:track:5V7qLbZJNTwaEVbZADqofc"
      },
      "played_at": "2022-12-02T09:23:20.978Z",
      "context": {
        "type": "playlist",
        "external_urls": {
          "spotify": "https://open.spotify.com/playlist/30B6dw5gD6kSl5TGfM22VY"
        },
        "href": "https://api.spotify.com/v1/playlists/30B6dw5gD6kSl5TGfM22VY",
        "uri": "spotify:playlist:30B6dw5gD6kSl5TGfM22VY"
      }
    }
  ]
}