{
  "items": [
    {
      "track": {
        "album": {
          "album_type": "album",
          "artists": [
            {
              "external_urls": {
                "spotify": "https://open.spotify.com/artist/3Y7Q8beSEoY8sVuyFzEopP"
              },
              "href": "https://api.spotify.com/v1/artists/3Y7Q8beSEoY8sVuyFzEopP",
              "id": "3Y7Q8beSEoY8sVuyFzEopP",
              "name": "A Film in Color",
              "type": "artist",
              "uri": "spotify:artist:3Y7Q8beSEoY8sVuyFzEopP"
            }
          ],
          "available_markets": [
            "AD",
            "AE",
            "AG",
            "AL",
            "AM",
            "AO",
            "AR",
            "AT",
            "AU",
            "AZ",
            "BA",
            "BB",
            "BD",
            "BE",
            "BF",
            "BG",
            "BH",
            "BJ",
            "BN",
            "BO",
            "BR",
            "BS",
            "BT",
            "BW",
            "BZ",
            "CA",
            "CG",
            "CH",
            "CI",
            "CL",
            "CM",
            "CO",
            "CR",
            "CV",
            "CW",
            "CY",
            "CZ",
            "DE",
            "DJ",
            "DK",
            "DM",
            "DO",
            "DZ",
            "EC",
            "EE",
            "EG",
            "ES",
            "FI",
            "FJ",
            "FM",
            "FR",
            "GA",
            "GB",
            "GD",
            "GE",
            "GH",
            "GM",
            "GN",
            "GQ",
            "GR",
            "GT",
            "GW",
            "GY",
            "HK",
            "HN",
            "HR",
            "HT",
            "HU",
            "ID",
            "IE",
            "IL",
            "IN",
            "IS",
            "IT",
            "JM",
            "JO",
            "JP",
            "KE",
            "KG",
            "KH",
            "KI",
            "KM",
            "KN",
            "KR",
            "KW",
            "KZ",
            "LA",
            "LB",
            "LC",
            "LI",
            "LK",
            "LR",
            "LS",
            "LT",
            "LU",
            "LV",
            "MA",
            "MC",
            "MD",
            "ME",
            "MG",
            "MH",
            "MK",
            "ML",
            "MN",
            "MO",
            "MR",
            "MT",
            "MU",
            "MV",
            "MW",
            "MX",
            "MY",
            "MZ",
            "NA",
            "NE",
            "NG",
            "NI",
            "NL",
            "NO",
            "NP",
            "NR",
            "NZ",
            "OM",
            "PA",
            "PE",
            "PG",
            "PH",
            "PK",
            "PL",
            "PS",
            "PT",
            "PW",
            "PY",
            "QA",
            "RO",
            "RW",
            "SA",
            "SB",
            "SC",
            "SE",
            "SG",
            "SI",
            "SK",
            "SL",
            "SM",
            "SN",
            "SR",
            "ST",
            "SV",
            "SZ",
            "TD",
            "TG",
            "TH",
            "TJ",
            "TL",
            "TN",
            "TO",
            "TR",
            "TT",
            "TV",
            "TW",
            "TZ",
            "UA",
            "UG",
            "US",
            "UY",
            "UZ",
            "VC",
            "VE",
            "VN",
            "VU",
            "WS",
            "ZA",
            "ZM"
          ],
          "external_urls": {
            "spotify": "https://open.spotify.com/album/0BB3rsY2HLc4Sa9b5Kq8eU"
          },
          "href": "https://api.spotify.com/v1/albums/0BB3rsY2HLc4Sa9b5Kq8eU",
          "id": "0BB3rsY2HLc4Sa9b5Kq8eU",
          "images": [
            {
              "height": 640,
              "url": "https://i.scdn.co/image/ab67616d0000b273c82a45fdeddc2d0a1f677730",
              "width": 640
            },
            {
              "height": 300,
              "url": "https://i.scdn.co/image/ab67616d00001e02c82a45fdeddc2d0a1f677730",
              "width": 300
            },
            {
              "height": 64,
              "url": "https://i.scdn.co/image/ab67616d00004851c82a45fdeddc2d0a1f677730",
              "width": 64
            }
          ],
          "name": "They March in Endless Circles",
          "release_date": "2018-06-22",
          "release_date_precision": "day",
          "total_tracks": 6,
          "type": "album",
          "uri": "spotify:album:0BB3rsY2HLc4Sa9b5Kq8eU"
        },
        "artists": [
          {
            "external_urls": {
              "spotify": "https://open.spotify.com/artist/3Y7Q8beSEoY8sVuyFzEopP"
            },
            "href": "https://api.spotify.com/v1/artists/3Y7Q8beSEoY8sVuyFzEopP",
            "id": "3Y7Q8beSEoY8sVuyFzEopP",
            "name": "A Film in Color",
            "type": "artist",
            "uri": "spotify:artist:3Y7Q8beSEoY8sVuyFzEopP"
          }
        ],
        "available_markets": [
          "AD",
          "AE",
          "AG",
          "AL",
          "AM",
          "AO",
          "AR",
          "AT",
          "AU",
          "AZ",
          "BA",
          "BB",
          "BD",
          "BE",
          "BF",
          "BG",
          "BH",
          "BJ",
          "BN",
          "BO",
          "BR",
          "BS",
          "BT",
          "BW",
          "BZ",
          "CA",
          "CG",
          "CH",
          "CI",
          "CL",
          "CM",
          "CO",
          "CR",
          "CV",
          "CW",
          "CY",
          "CZ",
          "DE",
          "DJ",
          "DK",
          "DM",
          "DO",
          "DZ",
          "EC",
          "EE",
          "EG",
          "ES",
          "FI",
          "FJ",
          "FM",
          "FR",
          "GA",
          "GB",
          "GD",
          "GE",
          "GH",
          "GM",
          "GN",
          "GQ",
          "GR",
          "GT",
          "GW",
          "GY",
          "HK",
          "HN",
          "HR",
          "HT",
          "HU",
          "ID",
          "IE",
          "IL",
          "IN",
          "IS",
          "IT",
          "JM",
          "JO",
          "JP",
          "KE",
          "KG",
          "KH",
          "KI",
          "KM",
          "KN",
          "KR",
          "KW",
          "KZ",
          "LA",
          "LB",
          "LC",
          "LI",
          "LK",
          "LR",
          "LS",
          "LT",
          "LU",
          "LV",
          "MA",
          "MC",
          "MD",
          "ME",
          "MG",
          "MH",
          "MK",
          "ML",
          "MN",
          "MO",
          "MR",
          "MT",
          "MU",
          "MV",
          "MW",
          "MX",
          "MY",
          "MZ",
          "NA",
          "NE",
          "NG",
          "NI",
          "NL",
          "NO",
          "NP",
          "NR",
          "NZ",
          "OM",
          "PA",
          "PE",
          "PG",
          "PH",
          "PK",
          "PL",
          "PS",
          "PT",
          "PW",
          "PY",
          "QA",
          "RO",
          "RW",
          "SA",
          "SB",
          "SC",
          "SE",
          "SG",
          "SI",
          "SK",
          "SL",
          "SM",
          "SN",
          "SR",
          "ST",
          "SV",
          "SZ",
          "TD",
          "TG",
          "TH",
          "TJ",
          "TL",
          "TN",
          "TO",
          "TR",
          "TT",
          "TV",
          "TW",
          "TZ",
          "UA",
          "UG",
          "US",
          "UY",
          "UZ",
          "VC",
          "VE",
          "VN",
          "VU",
          "WS",
          "ZA",
          "ZM"
        ],
        "disc_number": 1,
        "duration_ms": 654592,
        "explicit": false,
        "external_ids": {
          "isrc": "USDUK1800033"
        },
        "external_urls": {
          "spotify": "https://open.spotify.com/track/7y6pGLjGEme21jsBlJ1mfh"
        },
        "href": "https://api.spotify.com/v1/tracks/7y6pGLjGEme21jsBlJ1mfh",
        "id": "7y6pGLjGEme21jsBlJ1mfh",
        "is_local": false,
        "name": "Procession",
        "popularity": 4,
        "preview_url": "https://p.scdn.co/mp3-preview/71289915da08b9735538e8a7de2b438dcf235497?cid=d91479fbfab04b6b84bc68559d2f97d2",
        "track_number": 5,
        "type": "track",
        "uri": "spotify:track:7y6pGLjGEme21jsBlJ1mfh"
      },
      "played_at": "2022-07-25T04:20:22.122Z",
      "context": {
        "external_urls": {
          "spotify": "https://open.spotify.com/playlist/5rPBW39Qw8IxJdLnKUgUNk"
        },
        "href": "https://api.spotify.com/v1/playlists/5rPBW39Qw8IxJdLnKUgUNk",
        "type": "playlist",
        "uri": "spotify:playlist:5rPBW39Qw8IxJdLnKUgUNk"
      }
    },
    {
      "track": {
        "album": {
          "album_type": "album",
          "artists": [
            {
              "external_urls": {
                "spotify": "https://open.spotify.com/artist/3Y7Q8beSEoY8sVuyFzEopP"
              },
              "href": "https://api.spotify.com/v1/artists/3Y7Q8beSEoY8sVuyFzEopP",
              "id": "3Y7Q8beSEoY8sVuyFzEopP",
              "name": "A Film in Color",
              "type": "artist",
              "uri": "spotify:artist:3Y7Q8beSEoY8sVuyFzEopP"
            }
          ],
          "available_markets": [
            "AD",
            "AE",
            "AG",
            "AM",
            "AO",
            "AR",
            "AT",
            "AU",
            "AZ",
            "BB",
            "BD",
            "BE",
            "BF",
            "BG",
            "BH",
            "BI",
            "BJ",
            "BN",
            "BO",
            "BR",
            "BS",
            "BT",
            "BW",
            "BZ",
            "CA",
            "CG",
            "CH",
            "CL",
            "CM",
            "CO",
            "CR",
            "CV",
            "CW",
            "CY",
            "CZ",
            "DE",
            "DJ",
            "DK",
            "DM",
            "DO",
            "DZ",
            "EC",
            "EE",
            "EG",
            "ES",
            "FI",
            "FJ",
            "FM",
            "FR",
            "GA",
            "GB",
            "GD",
            "GE",
            "GH",
            "GM",
            "GN",
            "GQ",
            "GR",
            "GT",
            "GW",
            "GY",
            "HK",
            "HN",
            "HT",
            "HU",
            "ID",
            "IE",
            "IL",
            "IN",
            "IS",
            "IT",
            "JM",
            "JO",
            "JP",
            "KE",
            "KG",
            "KH",
            "KI",
            "KM",
            "KN",
            "KR",
            "KW",
            "KZ",
            "LA",
            "LB",
            "LC",
            "LI",
            "LK",
            "LS",
            "LT",
            "LU",
            "LV",
            "MA",
            "MC",
            "MD",
            "MG",
            "MH",
            "ML",
            "MN",
            "MO",
            "MR",
            "MT",
            "MU",
            "MV",
            "MW",
            "MX",
            "MY",
            "MZ",
            "NA",
            "NE",
            "NG",
            "NI",
            "NL",
            "NO",
            "NP",
            "NR",
            "NZ",
            "OM",
            "PA",
            "PE",
            "PG",
            "PH",
            "PK",
            "PL",
            "PS",
            "PT",
            "PW",
            "PY",
            "QA",
            "RO",
            "RW",
            "SA",
            "SB",
            "SC",
            "SE",
            "SG",
            "SI",
            "SK",
            "SL",
            "SM",
            "SN",
            "SR",
            "ST",
            "SV",
            "SZ",
            "TD",
            "TG",
            "TH",
            "TJ",
            "TL",
            "TN",
            "TO",
            "TR",
            "TT",
            "TV",
            "TW",
            "TZ",
            "UA",
            "UG",
            "US",
            "UY",
            "UZ",
            "VC",
            "VE",
            "VN",
            "VU",
            "WS",
            "ZA",
            "ZM"
          ],
          "external_urls": {
            "spotify": "https://open.spotify.com/album/1PIIhiaABXBElhRjDBu1Cc"
          },
          "href": "https://api.spotify.com/v1/albums/1PIIhiaABXBElhRjDBu1Cc",
          "id": "1PIIhiaABXBElhRjDBu1Cc",
          "images": [
            {
              "height": 640,
              "url": "https://i.scdn.co/image/ab67616d0000b273799f0045920eef96a5fc5bff",
              "width": 640
            },
            {
              "height": 300,
              "url": "https://i.scdn.co/image/ab67616d00001e02799f0045920eef96a5fc5bff",
              "width": 300
            },
            {
              "height": 64,
              "url": "https://i.scdn.co/image/ab67616d00004851799f0045920eef96a5fc5bff",
              "width": 64
            }
          ],
          "name": "To Scale a Mountain (Deluxe)",
          "release_date": "2014-03-20",
          "release_date_precision": "day",
          "total_tracks": 4,
          "type": "album",
          "uri": "spotify:album:1PIIhiaABXBElhRjDBu1Cc"
        },
        "artists": [
          {
            "external_urls": {
              "spotify": "https://open.spotify.com/artist/3Y7Q8beSEoY8sVuyFzEopP"
            },
            "href": "https://api.spotify.com/v1/artists/3Y7Q8beSEoY8sVuyFzEopP",
            "id": "3Y7Q8beSEoY8sVuyFzEopP",
            "name": "A Film in Color",
            "type": "artist",
            "uri": "spotify:artist:3Y7Q8beSEoY8sVuyFzEopP"
          }
        ],
        "available_markets": [
          "AD",
          "AE",
          "AG",
          "AM",
          "AO",
          "AR",
          "AT",
          "AU",
          "AZ",
          "BB",
          "BD",
          "BE",
          "BF",
          "BG",
          "BH",
          "BI",
          "BJ",
          "BN",
          "BO",
          "BR",
          "BS",
          "BT",
          "BW",
          "BZ",
          "CA",
          "CG",
          "CH",
          "CL",
          "CM",
          "CO",
          "CR",
          "CV",
          "CW",
          "CY",
          "CZ",
          "DE",
          "DJ",
          "DK",
          "DM",
          "DO",
          "DZ",
          "EC",
          "EE",
          "EG",
          "ES",
          "FI",
          "FJ",
          "FM",
          "FR",
          "GA",
          "GB",
          "GD",
          "GE",
          "GH",
          "GM",
          "GN",
          "GQ",
          "GR",
          "GT",
          "GW",
          "GY",
          "HK",
          "HN",
          "HT",
          "HU",
          "ID",
          "IE",
          "IL",
          "IN",
          "IS",
          "IT",
          "JM",
          "JO",
          "JP",
          "KE",
          "KG",
          "KH",
          "KI",
          "KM",
          "KN",
          "KR",
          "KW",
          "KZ",
          "LA",
          "LB",
          "LC",
          "LI",
          "LK",
          "LS",
          "LT",
          "LU",
          "LV",
          "MA",
          "MC",
          "MD",
          "MG",
          "MH",
          "ML",
          "MN",
          "MO",
          "MR",
          "MT",
          "MU",
          "MV",
          "MW",
          "MX",
          "MY",
          "MZ",
          "NA",
          "NE",
          "NG",
          "NI",
          "NL",
          "NO",
          "NP",
          "NR",
          "NZ",
          "OM",
          "PA",
          "PE",
          "PG",
          "PH",
          "PK",
          "PL",
          "PS",
          "PT",
          "PW",
          "PY",
          "QA",
          "RO",
          "RW",
          "SA",
          "SB",
          "SC",
          "SE",
          "SG",
          "SI",
          "SK",
          "SL",
          "SM",
          "SN",
          "SR",
          "ST",
          "SV",
          "SZ",
          "TD",
          "TG",
          "TH",
          "TJ",
          "TL",
          "TN",
          "TO",
          "TR",
          "TT",
          "TV",
          "TW",
          "TZ",
          "UA",
          "UG",
          "US",
          "UY",
          "UZ",
          "VC",
          "VE",
          "VN",
          "VU",
          "WS",
          "ZA",
          "ZM"
        ],
        "disc_number": 1,
        "duration_ms": 743654,
        "explicit": false,
        "external_ids": {
          "isrc": "TCADD1725146"
        },
        "external_urls": {
          "spotify": "https://open.spotify.com/track/1nyxDTgw0TRkRKY6l2JJMd"
        },
        "href": "https://api.spotify.com/v1/tracks/1nyxDTgw0TRkRKY6l2JJMd",
        "id": "1nyxDTgw0TRkRKY6l2JJMd",
        "is_local": false,
        "name": "II",
        "popularity": 2,
        "preview_url": "https://p.scdn.co/mp3-preview/9a918ac0b59c8dbf3b69fc31da00295d12fbec25?cid=d91479fbfab04b6b84bc68559d2f97d2",
        "track_number": 2,
        "type": "track",
        "uri": "spotify:track:1nyxDTgw0TRkRKY6l2JJMd"
      },
      "played_at": "2022-07-25T04:21:28.246Z",
      "context": {
        "external_urls": {
          "spotify": "https://open.spotify.com/playlist/5rPBW39Qw8IxJdLnKUgUNk"
        },
        "href": "https://api.spotify.com/v1/playlists/5rPBW39Qw8IxJdLnKUgUNk",
        "type": "playlist",
        "uri": "spotify:playlist:5rPBW39Qw8IxJdLnKUgUNk"
      }
    },
    {
      "track": {
        "album": {
          "album_type": "album",
          "artists": [
            {
              "external_urls": {
                "spotify": "https://open.spotify.com/artist/3Y7Q8beSEoY8sVuyFzEopP"
              },
              "href": "https://api.spotify.com/v1/artists/3Y7Q8beSEoY8sVuyFzEopP",
              "id": "3Y7Q8beSEoY8sVuyFzEopP",
              "name": "A Film in Color",
              "type": "artist",
              "uri": "spotify:artist:3Y7Q8beSEoY8sVuyFzEopP"
            }
          ],
          "available_markets": [
            "AD",
            "AE",
            "AG",
            "AM",
            "AO",
            "AR",
            "AT",
            "AU",
            "AZ",
            "BB",
            "BD",
            "BE",
            "BF",
            "BG",
            "BH",
            "BI",
            "BJ",
            "BN",
            "BO",
            "BR",
            "BS",
            "BT",
            "BW",
            "BZ",
            "CA",
            "CG",
            "CH",
            "CL",
            "CM",
            "CO",
            "CR",
            "CV",
            "CW",
            "CY",
            "CZ",
            "DE",
            "DJ",
            "DK",
            "DM",
            "DO",
            "DZ",
            "EC",
            "EE",
            "EG",
            "ES",
            "FI",
            "FJ",
            "FM",
            "FR",
            "GA",
            "GB",
            "GD",
            "GE",
            "GH",
            "GM",
            "GN",
            "GQ",
            "GR",
            "GT",
            "GW",
            "GY",
            "HK",
            "HN",
            "HT",
            "HU",
            "ID",
            "IE",
            "IL",
            "IN",
            "IS",
            "IT",
            "JM",
            "JO",
            "JP",
            "KE",
            "KG",
            "KH",
            "KI",
            "KM",
            "KN",
            "KR",
            "KW",
            "KZ",
            "LA",
            "LB",
            "LC",
            "LI",
            "LK",
            "LS",
            "LT",
            "LU",
            "LV",
            "MA",
            "MC",
            "MD",
            "MG",
            "MH",
            "ML",
            "MN",
            "MO",
            "MR",
            "MT",
            "MU",
            "MV",
            "MW",
            "MX",
            "MY",
            "MZ",
            "NA",
            "NE",
            "NG",
            "NI",
            "NL",
            "NO",
            "NP",
            "NR",
            "NZ",
            "OM",
            "PA",
            "PE",
            "PG",
            "PH",
            "PK",
            "PL",
            "PS",
            "PT",
            "PW",
            "PY",
            "QA",
            "RO",
            "RW",
            "SA",
            "SB",
            "SC",
            "SE",
            "SG",
            "SI",
            "SK",
            "SL",
            "SM",
            "SN",
            "SR",
            "ST",
            "SV",
            "SZ",
            "TD",
            "TG",
            "TH",
            "TJ",
            "TL",
            "TN",
            "TO",
            "TR",
            "TT",
            "TV",
            "TW",
            "TZ",
            "UA",
            "UG",
            "US",
            "UY",
            "UZ",
            "VC",
            "VE",
            "VN",
            "VU",
            "WS",
            "ZA",
            "ZM"
          ],
          "external_urls": {
            "spotify": "https://open.spotify.com/album/1PIIhiaABXBElhRjDBu1Cc"
          },
          "href": "https://api.spotify.com/v1/albums/1PIIhiaABXBElhRjDBu1Cc",
          "id": "1PIIhiaABXBElhRjDBu1Cc",
          "images": [
            {
              "height": 640,
              "url": "https://i.scdn.co/image/ab67616d0000b273799f0045920eef96a5fc5bff",
              "width": 640
            },
            {
              "height": 300,
              "url": "https://i.scdn.co/image/ab67616d00001e02799f0045920eef96a5fc5bff",
              "width": 300
            },
            {
              "height": 64,
              "url": "https://i.scdn.co/image/ab67616d00004851799f0045920eef96a5fc5bff",
              "width": 64
            }
          ],
          "name": "To Scale a Mountain (Deluxe)",
          "release_date": "2014-03-20",
          "release_date_precision": "day",
          "total_tracks": 4,
          "type": "album",
          "uri": "spotify:album:1PIIhiaABXBElhRjDBu1Cc"
        },
        "artists": [
          {
            "external_urls": {
              "spotify": "https://open.spotify.com/artist/3Y7Q8beSEoY8sVuyFzEopP"
            },
            "href": "https://api.spotify.com/v1/artists/3Y7Q8beSEoY8sVuyFzEopP",
            "id": "3Y7Q8beSEoY8sVuyFzEopP",
            "name": "A Film in Color",
            "type": "artist",
            "uri": "spotify:artist:3Y7Q8beSEoY8sVuyFzEopP"
          }
        ],
        "available_markets": [
          "AD",
          "AE",
          "AG",
          "AM",
          "AO",
          "AR",
          "AT",
          "AU",
          "AZ",
          "BB",
          "BD",
          "BE",
          "BF",
          "BG",
          "BH",
          "BI",
          "BJ",
          "BN",
          "BO",
          "BR",
          "BS",
          "BT",
          "BW",
          "BZ",
          "CA",
          "CG",
          "CH",
          "CL",
          "CM",
          "CO",
          "CR",
          "CV",
          "CW",
          "CY",
          "CZ",
          "DE",
          "DJ",
          "DK",
          "DM",
          "DO",
          "DZ",
          "EC",
          "EE",
          "EG",
          "ES",
          "FI",
          "FJ",
          "FM",
          "FR",
          "GA",
          "GB",
          "GD",
          "GE",
          "GH",
          "GM",
          "GN",
          "GQ",
          "GR",
          "GT",
          "GW",
          "GY",
          "HK",
          "HN",
          "HT",
          "HU",
          "ID",
          "IE",
          "IL",
          "IN",
          "IS",
          "IT",
          "JM",
          "JO",
          "JP",
          "KE",
          "KG",
          "KH",
          "KI",
          "KM",
          "KN",
          "KR",
          "KW",
          "KZ",
          "LA",
          "LB",
          "LC",
          "LI",
          "LK",
          "LS",
          "LT",
          "LU",
          "LV",
          "MA",
          "MC",
          "MD",
          "MG",
          "MH",
          "ML",
          "MN",
          "MO",
          "MR",
          "MT",
          "MU",
          "MV",
          "MW",
          "MX",
          "MY",
          "MZ",
          "NA",
          "NE",
          "NG",
          "NI",
          "NL",
          "NO",
          "NP",
          "NR",
          "NZ",
          "OM",
          "PA",
          "PE",
          "PG",
          "PH",
          "PK",
          "PL",
          "PS",
          "PT",
          "PW",
          "PY",
          "QA",
          "RO",
          "RW",
          "SA",
          "SB",
          "SC",
          "SE",
          "SG",
          "SI",
          "SK",
          "SL",
          "SM",
          "SN",
          "SR",
          "ST",
          "SV",
          "SZ",
          "TD",
          "TG",
          "TH",
          "TJ",
          "TL",
          "TN",
          "TO",
          "TR",
          "TT",
          "TV",
          "TW",
          "TZ",
          "UA",
          "UG",
          "US",
          "UY",
          "UZ",
          "VC",
          "VE",
          "VN",
          "VU",
          "WS",
          "ZA",
          "ZM"
        ],
        "disc_number": 1,
        "duration_ms": 743654,
        "explicit": false,
        "external_ids": {
          "isrc": "TCADD1725146"
        },
        "external_urls": {
          "spotify": "https://open.spotify.com/track/1nyxDTgw0TRkRKY6l2JJMd"
        },
        "href": "https://api.spotify.com/v1/tracks/1nyxDTgw0TRkRKY6l2JJMd",
        "id": "1nyxDTgw0TRkRKY6l2JJMd",
        "is_local": false,
        "name": "II",
        "popularity": 2,
        "preview_url": "https://p.scdn.co/mp3-preview/9a918ac0b59c8dbf3b69fc31da00295d12fbec25?cid=d91479fbfab04b6b84bc68559d2f97d2",
        "track_number": 2,
        "type": "track",
        "uri": "spotify:track:1nyxDTgw0TRkRKY6l2JJMd"
      },
      "played_at": "2022-07-25T04:21:37.279Z",
      "context": {
        "external_urls": {
          "spotify": "https://open.spotify.com/playlist/5rPBW39Qw8IxJdLnKUgUNk"
        },
        "href": "https://api.spotify.com/v1/playlists/5rPBW39Qw8IxJdLnKUgUNk",
        "type": "playlist",
        "uri": "spotify:playlist:5rPBW39Qw8IxJdLnKUgUNk"
      }
    },
    {
      "track": {
        "album": {
          "album_type": "album",
          "artists": [
            {
              "external_urls": {
                "spotify": "https://open.spotify.com/artist/3Y7Q8beSEoY8sVuyFzEopP"
              },
              "href": "https://api.spotify.com/v1/artists/3Y7Q8beSEoY8sVuyFzEopP",
              "id": "3Y7Q8beSEoY8sVuyFzEopP",
              "name": "A Film in Color",
              "type": "artist",
              "uri": "spotify:artist:3Y7Q8beSEoY8sVuyFzEopP"
            }
          ],
          "available_markets": [
            "AD",
            "AE",
            "AG",
            "AM",
            "AO",
            "AR",
            "AT",
            "AU",
            "AZ",
            "BB",
            "BD",
            "BE",
            "BF",
            "BG",
            "BH",
            "BI",
            "BJ",
            "BN",
            "BO",
            "BR",
            "BS",
            "BT",
            "BW",
            "BZ",
            "CA",
            "CG",
            "CH",
            "CL",
            "CM",
            "CO",
            "CR",
            "CV",
            "CW",
            "CY",
            "CZ",
            "DE",
            "DJ",
            "DK",
            "DM",
            "DO",
            "DZ",
            "EC",
            "EE",
            "EG",
            "ES",
            "FI",
            "FJ",
            "FM",
            "FR",
            "GA",
            "GB",
            "GD",
            "GE",
            "GH",
            "GM",
            "GN",
            "GQ",
            "GR",
            "GT",
            "GW",
            "GY",
            "HK",
            "HN",
            "HT",
            "HU",
            "ID",
            "IE",
            "IL",
            "IN",
            "IS",
            "IT",
            "JM",
            "JO",
            "JP",
            "KE",
            "KG",
            "KH",
            "KI",
            "KM",
            "KN",
            "KR",
            "KW",
            "KZ",
            "LA",
            "LB",
            "LC",
            "LI",
            "LK",
            "LS",
            "LT",
            "LU",
            "LV",
            "MA",
            "MC",
            "MD",
            "MG",
            "MH",
            "ML",
            "MN",
            "MO",
            "MR",
            "MT",
            "MU",
            "MV",
            "MW",
            "MX",
            "MY",
            "MZ",
            "NA",
            "NE",
            "NG",
            "NI",
            "NL",
            "NO",
            "NP",
            "NR",
            "NZ",
            "OM",
            "PA",
            "PE",
            "PG",
            "PH",
            "PK",
            "PL",
            "PS",
            "PT",
            "PW",
            "PY",
            "QA",
            "RO",
            "RW",
            "SA",
            "SB",
            "SC",
            "SE",
            "SG",
            "SI",
            "SK",
            "SL",
            "SM",
            "SN",
            "SR",
            "ST",
            "SV",
            "SZ",
            "TD",
            "TG",
            "TH",
            "TJ",
            "TL",
            "TN",
            "TO",
            "TR",
            "TT",
            "TV",
            "TW",
            "TZ",
            "UA",
            "UG",
            "US",
            "UY",
            "UZ",
            "VC",
            "VE",
            "VN",
            "VU",
            "WS",
            "ZA",
            "ZM"
          ],
          "external_urls": {
            "spotify": "https://open.spotify.com/album/1PIIhiaABXBElhRjDBu1Cc"
          },
          "href": "https://api.spotify.com/v1/albums/1PIIhiaABXBElhRjDBu1Cc",
          "id": "1PIIhiaABXBElhRjDBu1Cc",
          "images": [
            {
              "height": 640,
              "url": "https://i.scdn.co/image/ab67616d0000b273799f0045920eef96a5fc5bff",
              "width": 640
            },
            {
              "height": 300,
              "url": "https://i.scdn.co/image/ab67616d00001e02799f0045920eef96a5fc5bff",
              "width": 300
            },
            {
              "height": 64,
              "url": "https://i.scdn.co/image/ab67616d00004851799f0045920eef96a5fc5bff",
              "width": 64
            }
          ],
          "name": "To Scale a Mountain (Deluxe)",
          "release_date": "2014-03-20",
          "release_date_precision": "day",
          "total_tracks": 4,
          "type": "album",
          "uri": "spotify:album:1PIIhiaABXBElhRjDBu1Cc"
        },
        "artists": [
          {
            "external_urls": {
              "spotify": "https://open.spotify.com/artist/3Y7Q8beSEoY8sVuyFzEopP"
            },
            "href": "https://api.spotify.com/v1/artists/3Y7Q8beSEoY8sVuyFzEopP",
            "id": "3Y7Q8beSEoY8sVuyFzEopP",
            "name": "A Film in Color",
            "type": "artist",
            "uri": "spotify:artist:3Y7Q8beSEoY8sVuyFzEopP"
          }
        ],
        "available_markets": [
          "AD",
          "AE",
          "AG",
          "AM",
          "AO",
          "AR",
          "AT",
          "AU",
          "AZ",
          "BB",
          "BD",
          "BE",
          "BF",
          "BG",
          "BH",
          "BI",
          "BJ",
          "BN",
          "BO",
          "BR",
          "BS",
          "BT",
          "BW",
          "BZ",
          "CA",
          "CG",
          "CH",
          "CL",
          "CM",
          "CO",
          "CR",
          "CV",
          "CW",
          "CY",
          "CZ",
          "DE",
          "DJ",
          "DK",
          "DM",
          "DO",
          "DZ",
          "EC",
          "EE",
          "EG",
          "ES",
          "FI",
          "FJ",
          "FM",
          "FR",
          "GA",
          "GB",
          "GD",
          "GE",
          "GH",
          "GM",
          "GN",
          "GQ",
          "GR",
          "GT",
          "GW",
          "GY",
          "HK",
          "HN",
          "HT",
          "HU",
          "ID",
          "IE",
          "IL",
          "IN",
          "IS",
          "IT",
          "JM",
          "JO",
          "JP",
          "KE",
          "KG",
          "KH",
          "KI",
          "KM",
          "KN",
          "KR",
          "KW",
          "KZ",
          "LA",
          "LB",
          "LC",
          "LI",
          "LK",
          "LS",
          "LT",
          "LU",
          "LV",
          "MA",
          "MC",
          "MD",
          "MG",
          "MH",
          "ML",
          "MN",
          "MO",
          "MR",
          "MT",
          "MU",
          "MV",
          "MW",
          "MX",
          "MY",
          "MZ",
          "NA",
          "NE",
          "NG",
          "NI",
          "NL",
          "NO",
          "NP",
          "NR",
          "NZ",
          "OM",
          "PA",
          "PE",
          "PG",
          "PH",
          "PK",
          "PL",
          "PS",
          "PT",
          "PW",
          "PY",
          "QA",
          "RO",
          "RW",
          "SA",
          "SB",
          "SC",
          "SE",
          "SG",
          "SI",
          "SK",
          "SL",
          "SM",
          "SN",
          "SR",
          "ST",
          "SV",
          "SZ",
          "TD",
          "TG",
          "TH",
          "TJ",
          "TL",
          "TN",
          "TO",
          "TR",
          "TT",
          "TV",
          "TW",
          "TZ",
          "UA",
          "UG",
          "US",
          "UY",
          "UZ",
          "VC",
          "VE",
          "VN",
          "VU",
          "WS",
          "ZA",
          "ZM"
        ],
        "disc_number": 1,
        "duration_ms": 743654,
        "explicit": false,
        "external_ids": {
          "isrc": "TCADD1725146"
        },
        "external_urls": {
          "spotify": "https://open.spotify.com/track/1nyxDTgw0TRkRKY6l2JJMd"
        },
        "href": "https://api.spotify.com/v1/tracks/1nyxDTgw0TRkRKY6l2JJMd",
        "id": "1nyxDTgw0TRkRKY6l2JJMd",
        "is_local": false,
        "name": "II",
        "popularity": 2,
        "preview_url": "https://p.scdn.co/mp3-preview/9a918ac0b59c8dbf3b69fc31da00295d12fbec25?cid=d91479fbfab04b6b84bc68559d2f97d2",
        "track_number": 2,
        "type": "track",
        "uri": "spotify:track:1nyxDTgw0TRkRKY6l2JJMd"
      },
      "played_at": "2022-07-25T04:21:40.242Z",
      "context": {
        "external_urls": {
          "spotify": "https://open.spotify.com/playlist/5rPBW39Qw8IxJdLnKUgUNk"
        },
        "href": "https://api.spotify.com/v1/playlists/5rPBW39Qw8IxJdLnKUgUNk",
        "type": "playlist",
        "uri": "spotify:playlist:5rPBW39Qw8IxJdLnKUgUNk"
      }
    },
    {
      "track": {
        "album": {
          "album_type": "album",
          "artists": [
            {
              "external_urls": {
                "spotify": "https://open.spotify.com/artist/3Y7Q8beSEoY8sVuyFzEopP"
              },
              "href": "https://api.spotify.com/v1/artists/3Y7Q8beSEoY8sVuyFzEopP",
              "id": "3Y7Q8beSEoY8sVuyFzEopP",
              "name": "A Film in Color",
              "type": "artist",
              "uri": "spotify:artist:3Y7Q8beSEoY8sVuyFzEopP"
            }
          ],
          "available_markets": [
            "AD",
            "AE",
            "AG",
            "AM",
            "AO",
            "AR",
            "AT",
            "AU",
            "AZ",
            "BB",
            "BD",
            "BE",
            "BF",
            "BG",
            "BH",
            "BI",
            "BJ",
            "BN",
            "BO",
            "BR",
            "BS",
            "BT",
            "BW",
            "BZ",
            "CA",
            "CG",
            "CH",
            "CL",
            "CM",
            "CO",
            "CR",
            "CV",
            "CW",
            "CY",
            "CZ",
            "DE",
            "DJ",
            "DK",
            "DM",
            "DO",
            "DZ",
            "EC",
            "EE",
            "EG",
            "ES",
            "FI",
            "FJ",
            "FM",
            "FR",
            "GA",
            "GB",
            "GD",
            "GE",
            "GH",
            "GM",
            "GN",
            "GQ",
            "GR",
            "GT",
            "GW",
            "GY",
            "HK",
            "HN",
            "HT",
            "HU",
            "ID",
            "IE",
            "IL",
            "IN",
            "IS",
            "IT",
            "JM",
            "JO",
            "JP",
            "KE",
            "KG",
            "KH",
            "KI",
            "KM",
            "KN",
            "KR",
            "KW",
            "KZ",
            "LA",
            "LB",
            "LC",
            "LI",
            "LK",
            "LS",
            "LT",
            "LU",
            "LV",
            "MA",
            "MC",
            "MD",
            "MG",
            "MH",
            "ML",
            "MN",
            "MO",
            "MR",
            "MT",
            "MU",
            "MV",
            "MW",
            "MX",
            "MY",
            "MZ",
            "NA",
            "NE",
            "NG",
            "NI",
            "NL",
            "NO",
            "NP",
            "NR",
            "NZ",
            "OM",
            "PA",
            "PE",
            "PG",
            "PH",
            "PK",
            "PL",
            "PS",
            "PT",
            "PW",
            "PY",
            "QA",
            "RO",
            "RW",
            "SA",
            "SB",
            "SC",
            "SE",
            "SG",
            "SI",
            "SK",
            "SL",
            "SM",
            "SN",
            "SR",
            "ST",
            "SV",
            "SZ",
            "TD",
            "TG",
            "TH",
            "TJ",
            "TL",
            "TN",
            "TO",
            "TR",
            "TT",
            "TV",
            "TW",
            "TZ",
            "UA",
            "UG",
            "US",
            "UY",
            "UZ",
            "VC",
            "VE",
            "VN",
            "VU",
            "WS",
            "ZA",
            "ZM"
          ],
          "external_urls": {
            "spotify": "https://open.spotify.com/album/1PIIhiaABXBElhRjDBu1Cc"
          },
          "href": "https://api.spotify.com/v1/albums/1PIIhiaABXBElhRjDBu1Cc",
          "id": "1PIIhiaABXBElhRjDBu1Cc",
          "images": [
            {
              "height": 640,
              "url": "https://i.scdn.co/image/ab67616d0000b273799f0045920eef96a5fc5bff",
              "width": 640
            },
            {
              "height": 300,
              "url": "https://i.scdn.co/image/ab67616d00001e02799f0045920eef96a5fc5bff",
              "width": 300
            },
            {
              "height": 64,
              "url": "https://i.scdn.co/image/ab67616d00004851799f0045920eef96a5fc5bff",
              "width": 64
            }
          ],
          "name": "To Scale a Mountain (Deluxe)",
          "release_date": "2014-03-20",
          "release_date_precision": "day",
          "total_tracks": 4,
          "type": "album",
          "uri": "spotify:album:1PIIhiaABXBElhRjDBu1Cc"
        },
        "artists": [
          {
            "external_urls": {
              "spotify": "https://open.spotify.com/artist/3Y7Q8beSEoY8sVuyFzEopP"
            },
            "href": "https://api.spotify.com/v1/artists/3Y7Q8beSEoY8sVuyFzEopP",
            "id": "3Y7Q8beSEoY8sVuyFzEopP",
            "name": "A Film in Color",
            "type": "artist",
            "uri": "spotify:artist:3Y7Q8beSEoY8sVuyFzEopP"
          }
        ],
        "available_markets": [
          "AD",
          "AE",
          "AG",
          "AM",
          "AO",
          "AR",
          "AT",
          "AU",
          "AZ",
          "BB",
          "BD",
          "BE",
          "BF",
          "BG",
          "BH",
          "BI",
          "BJ",
          "BN",
          "BO",
          "BR",
          "BS",
          "BT",
          "BW",
          "BZ",
          "CA",
          "CG",
          "CH",
          "CL",
          "CM",
          "CO",
          "CR",
          "CV",
          "CW",
          "CY",
          "CZ",
          "DE",
          "DJ",
          "DK",
          "DM",
          "DO",
          "DZ",
          "EC",
          "EE",
          "EG",
          "ES",
          "FI",
          "FJ",
          "FM",
          "FR",
          "GA",
          "GB",
          "GD",
          "GE",
          "GH",
          "GM",
          "GN",
          "GQ",
          "GR",
          "GT",
          "GW",
          "GY",
          "HK",
          "HN",
          "HT",
          "HU",
          "ID",
          "IE",
          "IL",
          "IN",
          "IS",
          "IT",
          "JM",
          "JO",
          "JP",
          "KE",
          "KG",
          "KH",
          "KI",
          "KM",
          "KN",
          "KR",
          "KW",
          "KZ",
          "LA",
          "LB",
          "LC",
          "LI",
          "LK",
          "LS",
          "LT",
          "LU",
          "LV",
          "MA",
          "MC",
          "MD",
          "MG",
          "MH",
          "ML",
          "MN",
          "MO",
          "MR",
          "MT",
          "MU",
          "MV",
          "MW",
          "MX",
          "MY",
          "MZ",
          "NA",
          "NE",
          "NG",
          "NI",
          "NL",
          "NO",
          "NP",
          "NR",
          "NZ",
          "OM",
          "PA",
          "PE",
          "PG",
          "PH",
          "PK",
          "PL",
          "PS",
          "PT",
          "PW",
          "PY",
          "QA",
          "RO",
          "RW",
          "SA",
          "SB",
          "SC",
          "SE",
          "SG",
          "SI",
          "SK",
          "SL",
          "SM",
          "SN",
          "SR",
          "ST",
          "SV",
          "SZ",
          "TD",
          "TG",
          "TH",
          "TJ",
          "TL",
          "TN",
          "TO",
          "TR",
          "TT",
          "TV",
          "TW",
          "TZ",
          "UA",
          "UG",
          "US",
          "UY",
          "UZ",
          "VC",
          "VE",
          "VN",
          "VU",
          "WS",
          "ZA",
          "ZM"
        ],
        "disc_number": 1,
        "duration_ms": 743654,
        "explicit": false,
        "external_ids": {
          "isrc": "TCADD1725146"
        },
        "external_urls": {
          "spotify": "https://open.spotify.com/track/1nyxDTgw0TRkRKY6l2JJMd"
        },
        "href": "https://api.spotify.com/v1/tracks/1nyxDTgw0TRkRKY6l2JJMd",
        "id": "1nyxDTgw0TRkRKY6l2JJMd",
        "is_local": false,
        "name": "II",
        "popularity": 2,
        "preview_url": "https://p.scdn.co/mp3-preview/9a918ac0b59c8dbf3b69fc31da00295d12fbec25?cid=d91479fbfab04b6b84bc68559d2f97d2",
        "track_number": 2,
        "type": "track",
        "uri": "spotify:track:1nyxDTgw0TRkRKY6l2JJMd"
      },
      "played_at": "2022-07-25T04:27:09.216Z",
      "context": {
        "external_urls": {
          "spotify": "https://open.spotify.com/playlist/5rPBW39Qw8IxJdLnKUgUNk"
        },
        "href": "https://api.spotify.com/v1/playlists/5rPBW39Qw8IxJdLnKUgUNk",
        "type": "playlist",
        "uri": "spotify:playlist:5rPBW39Qw8IxJdLnKUgUNk"
      }
    },
    {
      "track": {
        "album": {
          "album_type": "album",
          "artists": [
            {
              "external_urls": {
                "spotify": "https://open.spotify.com/artist/2SY6OktZyMLdOnscX3DCyS"
              },
              "href": "https://api.spotify.com/v1/artists/2SY6OktZyMLdOnscX3DCyS",
              "id": "2SY6OktZyMLdOnscX3DCyS",
              "name": "JANNABI",
              "type": "artist",
              "uri": "spotify:artist:2SY6OktZyMLdOnscX3DCyS"
            }
          ],
          "available_markets": [
            "AD",
            "AE",
            "AG",
            "AL",
            "AM",
            "AO",
            "AR",
            "AT",
            "AU",
            "AZ",
            "BA",
            "BB",
            "BD",
            "BE",
            "BF",
            "BG",
            "BH",
            "BI",
            "BJ",
            "BN",
            "BO",
            "BR",
            "BS",
            "BT",
            "BW",
            "BY",
            "BZ",
            "CA",
            "CD",
            "CG",
            "CH",
            "CI",
            "CL",
            "CM",
            "CO",
            "CR",
            "CV",
            "CW",
            "CY",
            "CZ",
            "DE",
            "DJ",
            "DK",
            "DM",
            "DO",
            "DZ",
            "EC",
            "EE",
            "EG",
            "ES",
            "FI",
            "FJ",
            "FM",
            "FR",
            "GA",
            "GB",
            "GD",
            "GE",
            "GH",
            "GM",
            "GN",
            "GQ",
            "GR",
            "GT",
            "GW",
            "GY",
            "HK",
            "HN",
            "HR",
            "HT",
            "HU",
            "ID",
            "IE",
            "IL",
            "IN",
            "IQ",
            "IS",
            "IT",
            "JM",
            "JO",
            "JP",
            "KE",
            "KG",
            "KH",
            "KI",
            "KM",
            "KN",
            "KR",
            "KW",
            "KZ",
            "LA",
            "LB",
            "LC",
            "LI",
            "LK",
            "LR",
            "LS",
            "LT",
            "LU",
            "LV",
            "LY",
            "MA",
            "MC",
            "MD",
            "ME",
            "MG",
            "MH",
            "MK",
            "ML",
            "MN",
            "MO",
            "MR",
            "MT",
            "MU",
            "MV",
            "MW",
            "MX",
            "MY",
            "MZ",
            "NA",
            "NE",
            "NG",
            "NI",
            "NL",
            "NO",
            "NP",
            "NR",
            "NZ",
            "OM",
            "PA",
            "PE",
            "PG",
            "PH",
            "PK",
            "PL",
            "PS",
            "PT",
            "PW",
            "PY",
            "QA",
            "RO",
            "RS",
            "RW",
            "SA",
            "SB",
            "SC",
            "SE",
            "SG",
            "SI",
            "SK",
            "SL",
            "SM",
            "SN",
            "SR",
            "ST",
            "SV",
            "SZ",
            "TD",
            "TG",
            "TH",
            "TJ",
            "TL",
            "TN",
            "TO",
            "TR",
            "TT",
            "TV",
            "TW",
            "TZ",
            "UA",
            "UG",
            "US",
            "UY",
            "UZ",
            "VC",
            "VE",
            "VN",
            "VU",
            "WS",
            "XK",
            "ZA",
            "ZM",
            "ZW"
          ],
          "external_urls": {
            "spotify": "https://open.spotify.com/album/28GiIRNu9nEugqnUci3aIC"
          },
          "href": "https://api.spotify.com/v1/albums/28GiIRNu9nEugqnUci3aIC",
          "id": "28GiIRNu9nEugqnUci3aIC",
          "images": [
            {
              "height": 640,
              "url": "https://i.scdn.co/image/ab67616d0000b273f694adfa02990eaca79fec1b",
              "width": 640
            },
            {
              "height": 300,
              "url": "https://i.scdn.co/image/ab67616d00001e02f694adfa02990eaca79fec1b",
              "width": 300
            },
            {
              "height": 64,
              "url": "https://i.scdn.co/image/ab67616d00004851f694adfa02990eaca79fec1b",
              "width": 64
            }
          ],
          "name": "LEGEND",
          "release_date": "2019-03-13",
          "release_date_precision": "day",
          "total_tracks": 12,
          "type": "album",
          "uri": "spotify:album:28GiIRNu9nEugqnUci3aIC"
        },
        "artists": [
          {
            "external_urls": {
              "spotify": "https://open.spotify.com/artist/2SY6OktZyMLdOnscX3DCyS"
            },
            "href": "https://api.spotify.com/v1/artists/2SY6OktZyMLdOnscX3DCyS",
            "id": "2SY6OktZyMLdOnscX3DCyS",
            "name": "JANNABI",
            "type": "artist",
            "uri": "spotify:artist:2SY6OktZyMLdOnscX3DCyS"
          }
        ],
        "available_markets": [
          "AD",
          "AE",
          "AG",
          "AL",
          "AM",
          "AO",
          "AR",
          "AT",
          "AU",
          "AZ",
          "BA",
          "BB",
          "BD",
          "BE",
          "BF",
          "BG",
          "BH",
          "BI",
          "BJ",
          "BN",
          "BO",
          "BR",
          "BS",
          "BT",
          "BW",
          "BY",
          "BZ",
          "CA",
          "CD",
          "CG",
          "CH",
          "CI",
          "CL",
          "CM",
          "CO",
          "CR",
          "CV",
          "CW",
          "CY",
          "CZ",
          "DE",
          "DJ",
          "DK",
          "DM",
          "DO",
          "DZ",
          "EC",
          "EE",
          "EG",
          "ES",
          "FI",
          "FJ",
          "FM",
          "FR",
          "GA",
          "GB",
          "GD",
          "GE",
          "GH",
          "GM",
          "GN",
          "GQ",
          "GR",
          "GT",
          "GW",
          "GY",
          "HK",
          "HN",
          "HR",
          "HT",
          "HU",
          "ID",
          "IE",
          "IL",
          "IN",
          "IQ",
          "IS",
          "IT",
          "JM",
          "JO",
          "JP",
          "KE",
          "KG",
          "KH",
          "KI",
          "KM",
          "KN",
          "KR",
          "KW",
          "KZ",
          "LA",
          "LB",
          "LC",
          "LI",
          "LK",
          "LR",
          "LS",
          "LT",
          "LU",
          "LV",
          "LY",
          "MA",
          "MC",
          "MD",
          "ME",
          "MG",
          "MH",
          "MK",
          "ML",
          "MN",
          "MO",
          "MR",
          "MT",
          "MU",
          "MV",
          "MW",
          "MX",
          "MY",
          "MZ",
          "NA",
          "NE",
          "NG",
          "NI",
          "NL",
          "NO",
          "NP",
          "NR",
          "NZ",
          "OM",
          "PA",
          "PE",
          "PG",
          "PH",
          "PK",
          "PL",
          "PS",
          "PT",
          "PW",
          "PY",
          "QA",
          "RO",
          "RS",
          "RW",
          "SA",
          "SB",
          "SC",
          "SE",
          "SG",
          "SI",
          "SK",
          "SL",
          "SM",
          "SN",
          "SR",
          "ST",
          "SV",
          "SZ",
          "TD",
          "TG",
          "TH",
          "TJ",
          "TL",
          "TN",
          "TO",
          "TR",
          "TT",
          "TV",
          "TW",
          "TZ",
          "UA",
          "UG",
          "US",
          "UY",
          "UZ",
          "VC",
          "VE",
          "VN",
          "VU",
          "WS",
          "XK",
          "ZA",
          "ZM",
          "ZW"
        ],
        "disc_number": 1,
        "duration_ms": 265000,
        "explicit": false,
        "external_ids": {
          "isrc": "KRA381900671"
        },
        "external_urls": {
          "spotify": "https://open.spotify.com/track/5BqwC9kOBbqYkzdOKeXFFk"
        },
        "href": "https://api.spotify.com/v1/tracks/5BqwC9kOBbqYkzdOKeXFFk",
        "id": "5BqwC9kOBbqYkzdOKeXFFk",
        "is_local": false,
        "name": "for lovers who hesitate",
        "popularity": 60,
        "preview_url": "https://p.scdn.co/mp3-preview/7be1aa1e025c5e9e8dee704f7386d8064f15f7e0?cid=d91479fbfab04b6b84bc68559d2f97d2",
        "track_number": 8,
        "type": "track",
        "uri": "spotify:track:5BqwC9kOBbqYkzdOKeXFFk"
      },
      "played_at": "2022-07-25T04:37:30.162Z",
      "context": {
        "external_urls": {
          "spotify": "https://open.spotify.com/artist/2SY6OktZyMLdOnscX3DCyS"
        },
        "href": "https://api.spotify.com/v1/artists/2SY6OktZyMLdOnscX3DCyS",
        "type": "artist",
        "uri": "spotify:artist:2SY6OktZyMLdOnscX3DCyS"
      }
    },
    {
      "track": {
        "album": {
          "album_type": "single",
          "artists": [
            {
              "external_urls": {
                "spotify": "https://open.spotify.com/artist/2SY6OktZyMLdOnscX3DCyS"
              },
              "href": "https://api.spotify.com/v1/artists/2SY6OktZyMLdOnscX3DCyS",
              "id": "2SY6OktZyMLdOnscX3DCyS",
              "name": "JANNABI",
              "type": "artist",
              "uri": "spotify:artist:2SY6OktZyMLdOnscX3DCyS"
            }
          ],
          "available_markets": [
            "AD",
            "AE",
            "AG",
            "AL",
            "AM",
            "AO",
            "AR",
            "AT",
            "AU",
            "AZ",
            "BA",
            "BB",
            "BD",
            "BE",
            "BF",
            "BG",
            "BH",
            "BI",
            "BJ",
            "BN",
            "BO",
            "BR",
            "BS",
            "BT",
            "BW",
            "BY",
            "BZ",
            "CA",
            "CD",
            "CG",
            "CH",
            "CI",
            "CL",
            "CM",
            "CO",
            "CR",
            "CV",
            "CW",
            "CY",
            "CZ",
            "DE",
            "DJ",
            "DK",
            "DM",
            "DO",
            "DZ",
            "EC",
            "EE",
            "EG",
            "ES",
            "FI",
            "FJ",
            "FM",
            "FR",
            "GA",
            "GB",
            "GD",
            "GE",
            "GH",
            "GM",
            "GN",
            "GQ",
            "GR",
            "GT",
            "GW",
            "GY",
            "HK",
            "HN",
            "HR",
            "HT",
            "HU",
            "ID",
            "IE",
            "IL",
            "IN",
            "IQ",
            "IS",
            "IT",
            "JM",
            "JO",
            "JP",
            "KE",
            "KG",
            "KH",
            "KI",
            "KM",
            "KN",
            "KR",
            "KW",
            "KZ",
            "LA",
            "LB",
            "LC",
            "LI",
            "LK",
            "LR",
            "LS",
            "LT",
            "LU",
            "LV",
            "LY",
            "MA",
            "MC",
            "MD",
            "ME",
            "MG",
            "MH",
            "MK",
            "ML",
            "MN",
            "MO",
            "MR",
            "MT",
            "MU",
            "MV",
            "MW",
            "MX",
            "MY",
            "MZ",
            "NA",
            "NE",
            "NG",
            "NI",
            "NL",
            "NO",
            "NP",
            "NR",
            "NZ",
            "OM",
            "PA",
            "PE",
            "PG",
            "PH",
            "PK",
            "PL",
            "PS",
            "PT",
            "PW",
            "PY",
            "QA",
            "RO",
            "RS",
            "RW",
            "SA",
            "SB",
            "SC",
            "SE",
            "SG",
            "SI",
            "SK",
            "SL",
            "SM",
            "SN",
            "SR",
            "ST",
            "SV",
            "SZ",
            "TD",
            "TG",
            "TH",
            "TJ",
            "TL",
            "TN",
            "TO",
            "TR",
            "TT",
            "TV",
            "TW",
            "TZ",
            "UA",
            "UG",
            "US",
            "UY",
            "UZ",
            "VC",
            "VE",
            "VN",
            "VU",
            "WS",
            "XK",
            "ZA",
            "ZM",
            "ZW"
          ],
          "external_urls": {
            "spotify": "https://open.spotify.com/album/39YkUaoy7BMzsFvGGMwugk"
          },
          "href": "https://api.spotify.com/v1/albums/39YkUaoy7BMzsFvGGMwugk",
          "id": "39YkUaoy7BMzsFvGGMwugk",
          "images": [
            {
              "height": 640,
              "url": "https://i.scdn.co/image/ab67616d0000b273834e69858ed0f1b4ccbe0188",
              "width": 640
            },
            {
              "height": 300,
              "url": "https://i.scdn.co/image/ab67616d00001e02834e69858ed0f1b4ccbe0188",
              "width": 300
            },
            {
              "height": 64,
              "url": "https://i.scdn.co/image/ab67616d00004851834e69858ed0f1b4ccbe0188",
              "width": 64
            }
          ],
          "name": "JANNABI's Small Pieces l",
          "release_date": "2020-11-06",
          "release_date_precision": "day",
          "total_tracks": 5,
          "type": "album",
          "uri": "spotify:album:39YkUaoy7BMzsFvGGMwugk"
        },
        "artists": [
          {
            "external_urls": {
              "spotify": "https://open.spotify.com/artist/2SY6OktZyMLdOnscX3DCyS"
            },
            "href": "https://api.spotify.com/v1/artists/2SY6OktZyMLdOnscX3DCyS",
            "id": "2SY6OktZyMLdOnscX3DCyS",
            "name": "JANNABI",
            "type": "artist",
            "uri": "spotify:artist:2SY6OktZyMLdOnscX3DCyS"
          }
        ],
        "available_markets": [
          "AD",
          "AE",
          "AG",
          "AL",
          "AM",
          "AO",
          "AR",
          "AT",
          "AU",
          "AZ",
          "BA",
          "BB",
          "BD",
          "BE",
          "BF",
          "BG",
          "BH",
          "BI",
          "BJ",
          "BN",
          "BO",
          "BR",
          "BS",
          "BT",
          "BW",
          "BY",
          "BZ",
          "CA",
          "CD",
          "CG",
          "CH",
          "CI",
          "CL",
          "CM",
          "CO",
          "CR",
          "CV",
          "CW",
          "CY",
          "CZ",
          "DE",
          "DJ",
          "DK",
          "DM",
          "DO",
          "DZ",
          "EC",
          "EE",
          "EG",
          "ES",
          "FI",
          "FJ",
          "FM",
          "FR",
          "GA",
          "GB",
          "GD",
          "GE",
          "GH",
          "GM",
          "GN",
          "GQ",
          "GR",
          "GT",
          "GW",
          "GY",
          "HK",
          "HN",
          "HR",
          "HT",
          "HU",
          "ID",
          "IE",
          "IL",
          "IN",
          "IQ",
          "IS",
          "IT",
          "JM",
          "JO",
          "JP",
          "KE",
          "KG",
          "KH",
          "KI",
          "KM",
          "KN",
          "KR",
          "KW",
          "KZ",
          "LA",
          "LB",
          "LC",
          "LI",
          "LK",
          "LR",
          "LS",
          "LT",
          "LU",
          "LV",
          "LY",
          "MA",
          "MC",
          "MD",
          "ME",
          "MG",
          "MH",
          "MK",
          "ML",
          "MN",
          "MO",
          "MR",
          "MT",
          "MU",
          "MV",
          "MW",
          "MX",
          "MY",
          "MZ",
          "NA",
          "NE",
          "NG",
          "NI",
          "NL",
          "NO",
          "NP",
          "NR",
          "NZ",
          "OM",
          "PA",
          "PE",
          "PG",
          "PH",
          "PK",
          "PL",
          "PS",
          "PT",
          "PW",
          "PY",
          "QA",
          "RO",
          "RS",
          "RW",
          "SA",
          "SB",
          "SC",
          "SE",
          "SG",
          "SI",
          "SK",
          "SL",
          "SM",
          "SN",
          "SR",
          "ST",
          "SV",
          "SZ",
          "TD",
          "TG",
          "TH",
          "TJ",
          "TL",
          "TN",
          "TO",
          "TR",
          "TT",
          "TV",
          "TW",
          "TZ",
          "UA",
          "UG",
          "US",
          "UY",
          "UZ",
          "VC",
          "VE",
          "VN",
          "VU",
          "WS",
          "XK",
          "ZA",
          "ZM",
          "ZW"
        ],
        "disc_number": 1,
        "duration_ms": 187000,
        "explicit": false,
        "external_ids": {
          "isrc": "KRA382006276"
        },
        "external_urls": {
          "spotify": "https://open.spotify.com/track/4YaKlkNVJNbrIqN82EKFsQ"
        },
        "href": "https://api.spotify.com/v1/tracks/4YaKlkNVJNbrIqN82EKFsQ",
        "id": "4YaKlkNVJNbrIqN82EKFsQ",
        "is_local": false,
        "name": "A thought on an autumn night",
        "popularity": 51,
        "preview_url": "https://p.scdn.co/mp3-preview/cb885518058f80ba7444be3c4b35cfef21c84b5e?cid=d91479fbfab04b6b84bc68559d2f97d2",
        "track_number": 1,
        "type": "track",
        "uri": "spotify:track:4YaKlkNVJNbrIqN82EKFsQ"
      },
      "played_at": "2022-07-25T04:40:37.940Z",
      "context": {
        "external_urls": {
          "spotify": "https://open.spotify.com/artist/2SY6OktZyMLdOnscX3DCyS"
        },
        "href": "https://api.spotify.com/v1/artists/2SY6OktZyMLdOnscX3DCyS",
        "type": "artist",
        "uri": "spotify:artist:2SY6OktZyMLdOnscX3DCyS"
      }
    }
  ]
}